waves/Counter/rtl/Counter.v
// Generator : SpinalHDL v1.6.4    git head : 598c18959149eb18e5eee5b0aa3eef01ecaa41a1
// Component : Counter
// Git hash  : 89d7543c7219f82d1991c9174f1b313aba4435ca

`timescale 1ns/1ps 

module Counter (
  input               io_clear,
  output     [3:0]    io_value,
  output reg          io_full,
  input               clk,
  input               reset
);

  reg        [3:0]    counter_1;
  wire                when_Counter_l23;

  assign io_value = counter_1;
  always @(*) begin
    io_full = 1'b0;
    if(when_Counter_l23) begin
      io_full = 1'b1;
    end
  end

  assign when_Counter_l23 = (counter_1 == 4'b1111);
  always @(posedge clk or posedge reset) begin
    if(reset) begin
      counter_1 <= 4'b0000;
    end else begin
      counter_1 <= (counter_1 + 4'b0001);
      if(io_clear) begin
        counter_1 <= 4'b0000;
      end
    end
  end


endmodule

waves/Counter/test.vcd
$version Generated by VerilatedVcd $end
$date mar. 05 avril 2022 22:39:48 $end
$timescale 1ps $end

 $scope module TOP $end
  $var wire  1 & clk $end
  $var wire  1 # io_clear $end
  $var wire  1 % io_full $end
  $var wire  4 $ io_value [3:0] $end
  $var wire  1 ' reset $end
  $scope module Counter $end
   $var wire  1 & clk $end
   $var wire  4 ( counter_1 [3:0] $end
   $var wire  1 # io_clear $end
   $var wire  1 % io_full $end
   $var wire  4 $ io_value [3:0] $end
   $var wire  1 ' reset $end
   $var wire  1 ) when_Counter_l23 $end
  $upscope $end
 $upscope $end
$enddefinitions $end


#0
0#
b0000 $
0%
0&
1'
b0000 (
0)
#160
0'
#170
b0001 $
1&
b0001 (
#175
0&
#180
b0010 $
1&
b0010 (
#185
0&
#190
b0011 $
1&
b0011 (
#195
0&
#200
b0100 $
1&
b0100 (
#205
0&
#210
b0101 $
1&
b0101 (
#215
0&
#220
b0110 $
1&
b0110 (
#225
0&
#230
b0111 $
1&
b0111 (
#235
0&
#240
b1000 $
1&
b1000 (
#245
0&
#250
b1001 $
1&
b1001 (
#255
0&
#260
b1010 $
1&
b1010 (
#265
0&
#270
1#
b1011 $
1&
b1011 (
#275
0&
#280
b0000 $
1&
b0000 (
#285
0&
#290
0#
1&
#295
0&
#300
b0001 $
1&
b0001 (
#305
0&
#310
b0010 $
1&
b0010 (
#315
0&
#320
b0011 $
1&
b0011 (
#325
0&
#330
b0100 $
1&
b0100 (
#335
0&
#340
b0101 $
1&
b0101 (
#345
0&
#350
b0110 $
1&
b0110 (
#355
0&
#360
b0111 $
1&
b0111 (
#365
0&
#370
b1000 $
1&
b1000 (
#375
0&
#380
b1001 $
1&
b1001 (
#385
0&
#390
b1010 $
1&
b1010 (
#395
0&
#400
b1011 $
1&
b1011 (
#405
0&
#410
b1100 $
1&
b1100 (
#415
0&
#420
b1101 $
1&
b1101 (
#425
0&
#430
b1110 $
1&
b1110 (
#435
0&
#440
b1111 $
1%
1&
b1111 (
1)
#445
0&
#450
b0000 $
0%
1&
b0000 (
0)
#455
0&
#460
b0001 $
1&
b0001 (
#465
0&
#470
b0010 $
1&
b0010 (
#475
0&
#480
b0011 $
1&
b0011 (
#485
0&
#490
1#
b0100 $
1&
b0100 (
#495
0&
#500
0#
b0000 $
1&
b0000 (
#505
0&
#510
b0001 $
1&
b0001 (
#515
0&
#520
b0010 $
1&
b0010 (
#525
0&
#530
b0011 $
1&
b0011 (
#535
0&
#540
b0100 $
1&
b0100 (
#545
0&
#550
1#
b0101 $
1&
b0101 (
#555
0&
#560
0#
b0000 $
1&
b0000 (
#565
0&
#570
b0001 $
1&
b0001 (
#575
0&
#580
1#
b0010 $
1&
b0010 (
#585
0&
#590
0#
b0000 $
1&
b0000 (
#595
0&
#600
1#
b0001 $
1&
b0001 (
#605
0&
#610
b0000 $
1&
b0000 (
#615
0&
#620
0#
1&
#625
0&
#630
b0001 $
1&
b0001 (
#635
0&
#640
b0010 $
1&
b0010 (
#645
0&
#650
1#
b0011 $
1&
b0011 (
#655
0&
#660
0#
b0000 $
1&
b0000 (
#665
0&
#670
b0001 $
1&
b0001 (
#675
0&
#680
b0010 $
1&
b0010 (
#685
0&
#690
b0011 $
1&
b0011 (
#695
0&
#700
b0100 $
1&
b0100 (
#705
0&
#710
b0101 $
1&
b0101 (
#715
0&
#720
b0110 $
1&
b0110 (
#725
0&
#730
1#
b0111 $
1&
b0111 (
#735
0&
#740
b0000 $
1&
b0000 (
#745
0&
#750
0#
1&
#755
0&
#760
b0001 $
1&
b0001 (
#765
0&
#770
b0010 $
1&
b0010 (
#775
0&
#780
b0011 $
1&
b0011 (
#785
0&
#790
1#
b0100 $
1&
b0100 (
#795
0&
#800
0#
b0000 $
1&
b0000 (
#805
0&
#810
b0001 $
1&
b0001 (
#815
0&
#820
b0010 $
1&
b0010 (
#825
0&
#830
b0011 $
1&
b0011 (
#835
0&
#840
b0100 $
1&
b0100 (
#845
0&
#850
b0101 $
1&
b0101 (
#855
0&
#860
b0110 $
1&
b0110 (
#865
0&
#870
b0111 $
1&
b0111 (
#875
0&
#880
b1000 $
1&
b1000 (
#885
0&
#890
b1001 $
1&
b1001 (
#895
0&
#900
b1010 $
1&
b1010 (
#905
0&
#910
b1011 $
1&
b1011 (
#915
0&
#920
b1100 $
1&
b1100 (
#925
0&
#930
b1101 $
1&
b1101 (
#935
0&
#940
b1110 $
1&
b1110 (
#945
0&
#950
b1111 $
1%
1&
b1111 (
1)
#955
0&
#960
b0000 $
0%
1&
b0000 (
0)
#965
0&
#970
b0001 $
1&
b0001 (
#975
0&
#980
b0010 $
1&
b0010 (
#985
0&
#990
b0011 $
1&
b0011 (
#995
0&
#1000
b0100 $
1&
b0100 (
#1005
0&
#1010
b0101 $
1&
b0101 (
#1015
0&
#1020
b0110 $
1&
b0110 (
#1025
0&
#1030
1#
b0111 $
1&
b0111 (
#1035
0&
#1040
0#
b0000 $
1&
b0000 (
#1045
0&
#1050
b0001 $
1&
b0001 (
#1055
0&
#1060
b0010 $
1&
b0010 (
#1065
0&
#1070
b0011 $
1&
b0011 (
#1075
0&
#1080
b0100 $
1&
b0100 (
#1085
0&
#1090
b0101 $
1&
b0101 (
#1095
0&
#1100
b0110 $
1&
b0110 (
#1105
0&
#1110
1#
b0111 $
1&
b0111 (
#1115
0&
#1120
0#
b0000 $
1&
b0000 (
#1125
0&
#1130
b0001 $
1&
b0001 (
#1135
0&
#1140
b0010 $
1&
b0010 (
#1145
0&
#1150
b0011 $
1&
b0011 (
