rtl/Apb3Decoder.v
// Generator : SpinalHDL v1.6.4    git head : 598c18959149eb18e5eee5b0aa3eef01ecaa41a1
// Component : Apb3Decoder
// Git hash  : cf6312381553847f5e80d147d807b25f6b43ed95

`timescale 1ns/1ps 

module Apb3Decoder (
  input      [15:0]   io_input_PADDR,
  input      [0:0]    io_input_PSEL,
  input               io_input_PENABLE,
  output              io_input_PREADY,
  input               io_input_PWRITE,
  input      [31:0]   io_input_PWDATA,
  output     [31:0]   io_input_PRDATA,
  output              io_input_PSLVERROR,
  output     [15:0]   io_outputs_0_PADDR,
  output     [0:0]    io_outputs_0_PSEL,
  output              io_outputs_0_PENABLE,
  input               io_outputs_0_PREADY,
  output              io_outputs_0_PWRITE,
  output     [31:0]   io_outputs_0_PWDATA,
  input      [31:0]   io_outputs_0_PRDATA,
  input               io_outputs_0_PSLVERROR,
  output     [15:0]   io_outputs_1_PADDR,
  output     [0:0]    io_outputs_1_PSEL,
  output              io_outputs_1_PENABLE,
  input               io_outputs_1_PREADY,
  output              io_outputs_1_PWRITE,
  output     [31:0]   io_outputs_1_PWDATA,
  input      [31:0]   io_outputs_1_PRDATA,
  input               io_outputs_1_PSLVERROR,
  output     [15:0]   io_outputs_2_PADDR,
  output     [0:0]    io_outputs_2_PSEL,
  output              io_outputs_2_PENABLE,
  input               io_outputs_2_PREADY,
  output              io_outputs_2_PWRITE,
  output     [31:0]   io_outputs_2_PWDATA,
  input      [31:0]   io_outputs_2_PRDATA,
  input               io_outputs_2_PSLVERROR,
  output     [15:0]   io_outputs_3_PADDR,
  output     [0:0]    io_outputs_3_PSEL,
  output              io_outputs_3_PENABLE,
  input               io_outputs_3_PREADY,
  output              io_outputs_3_PWRITE,
  output     [31:0]   io_outputs_3_PWDATA,
  input      [31:0]   io_outputs_3_PRDATA,
  input               io_outputs_3_PSLVERROR
);

  reg                 _zz_io_input_PREADY;
  reg        [31:0]   _zz_io_input_PRDATA;
  reg                 _zz_io_input_PSLVERROR;
  wire                addressHit_0;
  wire                addressHit_1;
  wire                addressHit_2;
  wire                addressHit_3;
  wire                _zz_addressHitIndex;
  wire                _zz_addressHitIndex_1;
  wire       [1:0]    addressHitIndex;

  always @(*) begin
    case(addressHitIndex)
      2'b00 : begin
        _zz_io_input_PREADY = io_outputs_0_PREADY;
        _zz_io_input_PRDATA = io_outputs_0_PRDATA;
        _zz_io_input_PSLVERROR = io_outputs_0_PSLVERROR;
      end
      2'b01 : begin
        _zz_io_input_PREADY = io_outputs_1_PREADY;
        _zz_io_input_PRDATA = io_outputs_1_PRDATA;
        _zz_io_input_PSLVERROR = io_outputs_1_PSLVERROR;
      end
      2'b10 : begin
        _zz_io_input_PREADY = io_outputs_2_PREADY;
        _zz_io_input_PRDATA = io_outputs_2_PRDATA;
        _zz_io_input_PSLVERROR = io_outputs_2_PSLVERROR;
      end
      default : begin
        _zz_io_input_PREADY = io_outputs_3_PREADY;
        _zz_io_input_PRDATA = io_outputs_3_PRDATA;
        _zz_io_input_PSLVERROR = io_outputs_3_PSLVERROR;
      end
    endcase
  end

  assign io_outputs_0_PADDR = io_input_PADDR;
  assign io_outputs_0_PWRITE = io_input_PWRITE;
  assign io_outputs_0_PENABLE = io_input_PENABLE;
  assign io_outputs_0_PWDATA = io_input_PWDATA;
  assign io_outputs_1_PADDR = io_input_PADDR;
  assign io_outputs_1_PWRITE = io_input_PWRITE;
  assign io_outputs_1_PENABLE = io_input_PENABLE;
  assign io_outputs_1_PWDATA = io_input_PWDATA;
  assign io_outputs_2_PADDR = io_input_PADDR;
  assign io_outputs_2_PWRITE = io_input_PWRITE;
  assign io_outputs_2_PENABLE = io_input_PENABLE;
  assign io_outputs_2_PWDATA = io_input_PWDATA;
  assign io_outputs_3_PADDR = io_input_PADDR;
  assign io_outputs_3_PWRITE = io_input_PWRITE;
  assign io_outputs_3_PENABLE = io_input_PENABLE;
  assign io_outputs_3_PWDATA = io_input_PWDATA;
  assign addressHit_0 = ((16'h0 <= io_input_PADDR) && (io_input_PADDR < 16'h1000));
  assign addressHit_1 = ((16'h1000 <= io_input_PADDR) && (io_input_PADDR < 16'h2000));
  assign addressHit_2 = ((16'h4000 <= io_input_PADDR) && (io_input_PADDR < 16'h6000));
  assign addressHit_3 = ((16'h6000 <= io_input_PADDR) && (io_input_PADDR < 16'h9000));
  assign _zz_addressHitIndex = (addressHit_1 || addressHit_3);
  assign _zz_addressHitIndex_1 = (addressHit_2 || addressHit_3);
  assign addressHitIndex = {_zz_addressHitIndex_1,_zz_addressHitIndex};
  assign io_outputs_0_PSEL[0] = (addressHit_0 && io_input_PSEL[0]);
  assign io_outputs_1_PSEL[0] = (addressHit_1 && io_input_PSEL[0]);
  assign io_outputs_2_PSEL[0] = (addressHit_2 && io_input_PSEL[0]);
  assign io_outputs_3_PSEL[0] = (addressHit_3 && io_input_PSEL[0]);
  assign io_input_PREADY = _zz_io_input_PREADY;
  assign io_input_PRDATA = _zz_io_input_PRDATA;
  assign io_input_PSLVERROR = _zz_io_input_PSLVERROR;

  initial begin
    $dumpfile("../../../../../waves/Apb3Decoder.vcd");
    $dumpvars(0, Apb3Decoder);
  end

endmodule

waves/Apb3Decoder.vcd
$date
	Thu Apr 21 02:05:13 2022
$end
$version
	Icarus Verilog
$end
$timescale
	1ps
$end
$scope module Apb3Decoder $end
$var wire 1 ! _zz_addressHitIndex $end
$var wire 1 " _zz_addressHitIndex_1 $end
$var wire 1 # addressHit_0 $end
$var wire 1 $ addressHit_1 $end
$var wire 1 % addressHit_2 $end
$var wire 1 & addressHit_3 $end
$var wire 16 ' io_input_PADDR [15:0] $end
$var wire 1 ( io_input_PENABLE $end
$var wire 32 ) io_input_PRDATA [31:0] $end
$var wire 1 * io_input_PREADY $end
$var wire 1 + io_input_PSEL $end
$var wire 1 , io_input_PSLVERROR $end
$var wire 32 - io_input_PWDATA [31:0] $end
$var wire 1 . io_input_PWRITE $end
$var wire 16 / io_outputs_0_PADDR [15:0] $end
$var wire 1 0 io_outputs_0_PENABLE $end
$var wire 32 1 io_outputs_0_PRDATA [31:0] $end
$var wire 1 2 io_outputs_0_PREADY $end
$var wire 1 3 io_outputs_0_PSEL $end
$var wire 1 4 io_outputs_0_PSLVERROR $end
$var wire 32 5 io_outputs_0_PWDATA [31:0] $end
$var wire 1 6 io_outputs_0_PWRITE $end
$var wire 16 7 io_outputs_1_PADDR [15:0] $end
$var wire 1 8 io_outputs_1_PENABLE $end
$var wire 32 9 io_outputs_1_PRDATA [31:0] $end
$var wire 1 : io_outputs_1_PREADY $end
$var wire 1 ; io_outputs_1_PSEL $end
$var wire 1 < io_outputs_1_PSLVERROR $end
$var wire 32 = io_outputs_1_PWDATA [31:0] $end
$var wire 1 > io_outputs_1_PWRITE $end
$var wire 16 ? io_outputs_2_PADDR [15:0] $end
$var wire 1 @ io_outputs_2_PENABLE $end
$var wire 32 A io_outputs_2_PRDATA [31:0] $end
$var wire 1 B io_outputs_2_PREADY $end
$var wire 1 C io_outputs_2_PSEL $end
$var wire 1 D io_outputs_2_PSLVERROR $end
$var wire 32 E io_outputs_2_PWDATA [31:0] $end
$var wire 1 F io_outputs_2_PWRITE $end
$var wire 16 G io_outputs_3_PADDR [15:0] $end
$var wire 1 H io_outputs_3_PENABLE $end
$var wire 32 I io_outputs_3_PRDATA [31:0] $end
$var wire 1 J io_outputs_3_PREADY $end
$var wire 1 K io_outputs_3_PSEL $end
$var wire 1 L io_outputs_3_PSLVERROR $end
$var wire 32 M io_outputs_3_PWDATA [31:0] $end
$var wire 1 N io_outputs_3_PWRITE $end
$var wire 2 O addressHitIndex [1:0] $end
$var reg 32 P _zz_io_input_PRDATA [31:0] $end
$var reg 1 Q _zz_io_input_PREADY $end
$var reg 1 R _zz_io_input_PSLVERROR $end
$upscope $end
$enddefinitions $end
#0
$dumpvars
1R
0Q
b1000010010010000101111000111010 P
b0 O
1N
b1101011101010101001010001010101 M
0L
0K
0J
b11110111110000011011110110000111 I
1H
b1101100000101100 G
1F
b1101011101010101001010001010101 E
1D
0C
1B
b11001000101001110000011000111001 A
1@
b1101100000101100 ?
1>
b1101011101010101001010001010101 =
0<
0;
1:
b1111100011001011100000111100101 9
18
b1101100000101100 7
16
b1101011101010101001010001010101 5
14
03
02
b1000010010010000101111000111010 1
10
b1101100000101100 /
1.
b1101011101010101001010001010101 -
1,
0+
0*
b1000010010010000101111000111010 )
1(
b1101100000101100 '
0&
0%
0$
0#
0"
0!
$end
#1000
b10 O
1"
1C
1%
0,
0R
b11001100101001011010010110100001 )
b11001100101001011010010110100001 P
1*
1Q
b101101110101001 /
b101101110101001 7
b101101110101001 ?
b101101110101001 G
b101101110101001 '
1+
b110111111010111101110011011001 5
b110111111010111101110011011001 =
b110111111010111101110011011001 E
b110111111010111101110011011001 M
b110111111010111101110011011001 -
12
b100011101001110111000100011010 1
04
0:
b11000001011111000110001001111001 9
b11001100101001011010010110100001 A
0D
1J
b11101000111001010010000101101010 I
1L
#2000
0*
0Q
b0 O
0"
0C
0%
b1001111011001011101010011011001 )
b1001111011001011101010011011001 P
b1111101110010111 /
b1111101110010111 7
b1111101110010111 ?
b1111101110010111 G
b1111101110010111 '
b11100110111101000101100100001011 5
b11100110111101000101100100001011 =
b11100110111101000101100100001011 E
b11100110111101000101100100001011 M
b11100110111101000101100100001011 -
02
b1001111011001011101010011011001 1
1:
b10010111000001100100010110010 9
1<
b10101111000110011001001000101010 A
0J
b10001111010011111111001100011110 I
0L
#3000
b10 O
1"
1%
0,
0R
b10000101011101110110111010011010 )
b10000101011101110110111010011010 P
1*
1Q
b101101010010010 /
b101101010010010 7
b101101010010010 ?
b101101010010010 G
b101101010010010 '
0+
00
08
0@
0H
0(
b10100011111100101100100110111111 5
b10100011111100101100100110111111 =
b10100011111100101100100110111111 E
b10100011111100101100100110111111 M
b10100011111100101100100110111111 -
12
b110100010110001010011101001000 1
14
b1111010000111010101000000000110 9
0<
b10000101011101110110111010011010 A
b11001110000101100100110110111010 I
1L
#4000
0*
0Q
b11 O
1!
1K
0%
1&
0C
1,
1R
b11010011111110111111010001111010 )
b11010011111110111111010001111010 P
b1000110001110111 /
b1000110001110111 7
b1000110001110111 ?
b1000110001110111 G
b1000110001110111 '
1+
06
0>
0F
0N
0.
b10111000001111101001000011101100 5
b10111000001111101001000011101100 =
b10111000001111101001000011101100 E
b10111000001111101001000011101100 M
b10111000001111101001000011101100 -
b1100110000110010100110010110001 1
b11001000111110001110001111010000 9
1<
b10010101110010101000101 A
1D
b11010011111110111111010001111010 I
#5000
b10 O
0!
1%
0&
0K
b11001101101010000000010101101100 )
b11001101101010000000010101101100 P
b101010101001000 /
b101010101001000 7
b101010101001000 ?
b101010101001000 G
b101010101001000 '
0+
10
18
1@
1H
1(
b10110100001000011110101011101011 5
b10110100001000011110101011101011 =
b10110100001000011110101011101011 E
b10110100001000011110101011101011 M
b10110100001000011110101011101011 -
b10000000111111011110011001100 1
04
b10010001010010000110001001001111 9
0<
0B
b11001101101010000000010101101100 A
b11001101100111010010101101111101 I
#6000
1*
1Q
b11 O
1!
0%
1&
1,
1R
b11111111100111001100001001001 )
b11111111100111001100001001001 P
b111001010101110 /
b111001010101110 7
b111001010101110 ?
b111001010101110 G
b111001010101110 '
00
08
0@
0H
0(
16
1>
1F
1N
1.
b1010001111011110001100100100010 5
b1010001111011110001100100100010 =
b1010001111011110001100100100010 E
b1010001111011110001100100100010 M
b1010001111011110001100100100010 -
b10000010000010000110010111010110 1
14
b1111101010000011110011000000010 9
b10001101000111111101100110110111 A
0D
1J
b11111111100111001100001001001 I
#7000
0*
0Q
1C
b10 O
0!
1%
0&
0K
1,
1R
b10111011101010011001101101101 )
b10111011101010011001101101101 P
b101010100101111 /
b101010100101111 7
b101010100101111 ?
b101010100101111 G
b101010100101111 '
1+
10
18
1@
1H
1(
b110100000001010000100101011100 5
b110100000001010000100101011100 =
b110100000001010000100101011100 E
b110100000001010000100101011100 M
b110100000001010000100101011100 -
b11001100101001110100000101000111 1
b10010110011011100001001001110111 9
b10111011101010011001101101101 A
1D
b1100010100010001110000110100101 I
0L
#8000
1*
1Q
b0 O
0"
0%
0C
0,
0R
b101111110011011000000110110101 )
b101111110011011000000110110101 P
b1001001101011101 /
b1001001101011101 7
b1001001101011101 ?
b1001001101011101 G
b1001001101011101 '
0+
00
08
0@
0H
0(
06
0>
0F
0N
0.
b110000011110111111001100100110 5
b110000011110111111001100100110 =
b110000011110111111001100100110 E
b110000011110111111001100100110 M
b110000011110111111001100100110 -
b101111110011011000000110110101 1
04
b11111011001101100111010110111000 9
1<
b1111001111111011110111101111100 A
0D
0J
b10101101110000001101101001111010 I
1L
#9000
1,
1R
b10100100010110010011101011000 )
b10100100010110010011101011000 P
b10000101010110 /
b10000101010110 7
b10000101010110 ?
b10000101010110 G
b10000101010110 '
1+
16
1>
1F
1N
1.
b1001111001000110100111100110 5
b1001111001000110100111100110 =
b1001111001000110100111100110 E
b1001111001000110100111100110 M
b1001111001000110100111100110 -
b10100100010110010011101011000 1
14
b11101100010011110010000101111011 9
1B
b10101110111110011100000000001011 A
1J
b10110100100011010111001111110001 I
#10000
0,
0R
b10 O
1"
1C
1%
b10010100011001101110010001110010 )
b10010100011001101110010001110010 P
0*
0Q
b100011010001111 /
b100011010001111 7
b100011010001111 ?
b100011010001111 G
b100011010001111 '
10
18
1@
1H
1(
06
0>
0F
0N
0.
b11011001011101111110100110010011 5
b11011001011101111110100110010011 =
b11011001011101111110100110010011 E
b11011001011101111110100110010011 M
b11011001011101111110100110010011 -
02
b11100101001000010100011000000110 1
b11010011010001000111010010010000 9
0B
b10010100011001101110010001110010 A
0J
b1111110000111101010100111000101 I
#11000
1*
1Q
b0 O
0"
0C
0%
0,
0R
b1011011011111000111000010011010 )
b1011011011111000111000010011010 P
b1010010000100101 /
b1010010000100101 7
b1010010000100101 ?
b1010010000100101 G
b1010010000100101 '
16
1>
1F
1N
1.
b11111011100000101000011000001101 5
b11111011100000101000011000001101 =
b11111011100000101000011000001101 E
b11111011100000101000011000001101 M
b11111011100000101000011000001101 -
12
b1011011011111000111000010011010 1
04
0:
b10011100110111110101101010000110 9
0<
b10010110010010101000011100001100 A
1D
b11011000010101110000000100000010 I
0L
#12000
b111000011100000001101000010100 )
b111000011100000001101000010100 P
b11111000110111 /
b11111000110111 7
b11111000110111 ?
b11111000110111 G
b11111000110111 '
0+
06
0>
0F
0N
0.
b11101111111001000001101010010 5
b11101111111001000001101010010 =
b11101111111001000001101010010 E
b11101111111001000001101010010 M
b11101111111001000001101010010 -
b111000011100000001101000010100 1
1:
b101011101001001011000110000000 9
b11010000110111111010111001000011 A
0D
b11001000011110100111010001100011 I
#13000
1,
1R
b10100010010110110101100111111101 )
b10100010010110110101100111111101 P
b1101101011110110 /
b1101101011110110 7
b1101101011110110 ?
b1101101011110110 G
b1101101011110110 '
1+
00
08
0@
0H
0(
b11010001001011101100101111000100 5
b11010001001011101100101111000100 =
b11010001001011101100101111000100 E
b11010001001011101100101111000100 M
b11010001001011101100101111000100 -
b10100010010110110101100111111101 1
14
b10001000110000010011001010101101 9
1<
1B
b10010111100010111010111111111 A
b10100010100011110101101010110000 I
#14000
b1011110110000010111110110111110 )
b1011110110000010111110110111110 P
0*
0Q
b1001101100111000 /
b1001101100111000 7
b1001101100111000 ?
b1001101100111000 G
b1001101100111000 '
10
18
1@
1H
1(
b1100100001001100100110011010101 5
b1100100001001100100110011010101 =
b1100100001001100100110011010101 E
b1100100001001100100110011010101 M
b1100100001001100100110011010101 -
02
b1011110110000010111110110111110 1
b11101101101010011001100110100 9
0<
b101100010011111100001110111 A
1J
b11111000011111110100001111111101 I
#15000
b1111101000110100001001100110 )
b1111101000110100001001100110 P
1*
1Q
b1011011111010110 /
b1011011111010110 7
b1011011111010110 ?
b1011011111010110 G
b1011011111010110 '
0+
00
08
0@
0H
0(
b10111010001001101101100001010001 5
b10111010001001101101100001010001 =
b10111010001001101101100001010001 E
b10111010001001101101100001010001 M
b10111010001001101101100001010001 -
12
b1111101000110100001001100110 1
b101110101010001010000110011 9
1<
0B
b10011110110111111010001111011010 A
b1000010100010100001110000100010 I
#16000
0,
0R
b101110001010010101000001100101 )
b101110001010010101000001100101 P
0*
0Q
b11100010001000 /
b11100010001000 7
b11100010001000 ?
b11100010001000 G
b11100010001000 '
10
18
1@
1H
1(
b1011001101011001101110110011000 5
b1011001101011001101110110011000 =
b1011001101011001101110110011000 E
b1011001101011001101110110011000 M
b1011001101011001101110110011000 -
02
b101110001010010101000001100101 1
04
b1110111100101011110100110000110 9
0<
1B
b11001110101011111100101110000 A
1D
b1100100001010101010110101001000 I
#17000
b10 O
1"
1%
1,
1R
b110100000100101111110000010010 )
b110100000100101111110000010010 P
1*
1Q
b100001010011000 /
b100001010011000 7
b100001010011000 ?
b100001010011000 G
b100001010011000 '
16
1>
1F
1N
1.
b1111000011000000001011000000010 5
b1111000011000000001011000000010 =
b1111000011000000001011000000010 E
b1111000011000000001011000000010 M
b1111000011000000001011000000010 -
12
b11100110111111010110100011101000 1
14
b101011010111110110100100110010 9
1<
b110100000100101111110000010010 A
b1110110111000110110100101011 I
1L
#18000
b0 O
0"
0%
0,
0R
b1000000001011010000101110101111 )
b1000000001011010000101110101111 P
b1010110100011011 /
b1010110100011011 7
b1010110100011011 ?
b1010110100011011 G
b1010110100011011 '
06
0>
0F
0N
0.
b1010111101000011100101101110001 5
b1010111101000011100101101110001 =
b1010111101000011100101101110001 E
b1010111101000011100101101110001 M
b1010111101000011100101101110001 -
b1000000001011010000101110101111 1
04
b11101011111000100001001101101000 9
0<
b101100110000001111100001011001 A
0D
0J
b10101110011010000110100100001010 I
0L
#19000
b10100110001000001000000101000011 )
b10100110001000001000000101000011 P
0*
0Q
b1110011001101100 /
b1110011001101100 7
b1110011001101100 ?
b1110011001101100 G
b1110011001101100 '
1+
16
1>
1F
1N
1.
b11101010111000100000001001011110 5
b11101010111000100000001001011110 =
b11101010111000100000001001011110 E
b11101010111000100000001001011110 M
b11101010111000100000001001011110 -
02
b10100110001000001000000101000011 1
0:
b11010110011100001111011001101000 9
1<
0B
b100111010001100000111100100010 A
1D
1J
b11001011110000011011001010 I
#20000
b1000111111001111111010110010011 )
b1000111111001111111010110010011 P
1*
1Q
b1011110111010111 /
b1011110111010111 7
b1011110111010111 ?
b1011110111010111 G
b1011110111010111 '
0+
00
08
0@
0H
0(
b1011101100101100001111110000 5
b1011101100101100001111110000 =
b1011101100101100001111110000 E
b1011101100101100001111110000 M
b1011101100101100001111110000 -
12
b1000111111001111111010110010011 1
b11000011000111010101101010010111 9
b1011010001010110111010001011011 A
0J
b10101100011001000010101101001100 I
#21000
1,
1R
b100001111000010101000010010100 )
b100001111000010101000010010100 P
b1001011100011100 /
b1001011100011100 7
b1001011100011100 ?
b1001011100011100 G
b1001011100011100 '
1+
10
18
1@
1H
1(
b11011010100100001111010100110100 5
b11011010100100001111010100110100 =
b11011010100100001111010100110100 E
b11011010100100001111010100110100 M
b11011010100100001111010100110100 -
b100001111000010101000010010100 1
14
b1100011010101010001100011110111 9
b11010100001100101111100011011011 A
b11000111110010000101111 I
1L
#22000
0,
0R
b10100011001011001001101101101111 )
b10100011001011001001101101101111 P
0*
0Q
b11000100111011 /
b11000100111011 7
b11000100111011 ?
b11000100111011 G
b11000100111011 '
00
08
0@
0H
0(
06
0>
0F
0N
0.
b111101010010100101110101010001 5
b111101010010100101110101010001 =
b111101010010100101110101010001 E
b111101010010100101110101010001 M
b111101010010100101110101010001 -
02
b10100011001011001001101101101111 1
04
b10110101110110010111111011110111 9
1B
b10010001011100100101111100001010 A
b1000000100110101110101011000 I
0L
#23000
b10110101100000010110101101110100 )
b10110101100000010110101101110100 P
1*
1Q
b1101111100100110 /
b1101111100100110 7
b1101111100100110 ?
b1101111100100110 G
b1101111100100110 '
10
18
1@
1H
1(
b11000101101011011111011010000001 5
b11000101101011011111011010000001 =
b11000101101011011111011010000001 E
b11000101101011011111011010000001 M
b11000101101011011111011010000001 -
12
b10110101100000010110101101110100 1
b1110010000000101001100111100011 9
0<
0B
b10110011100101101001000001010111 A
0D
b10000111000011110000100001001100 I
1L
#24000
1,
1R
1!
b11 O
1"
1K
1&
b11010010100111011100010111011111 )
b11010010100111011100010111011111 P
1*
1Q
b111110010111101 /
b111110010111101 7
b111110010111101 ?
b111110010111101 G
b111110010111101 '
16
1>
1F
1N
1.
b11000001011001110111001100111111 5
b11000001011001110111001100111111 =
b11000001011001110111001100111111 E
b11000001011001110111001100111111 M
b11000001011001110111001100111111 -
02
b11100010010001011010010001100000 1
b1010011011100010000111101010111 9
1B
b1110111100001100011111111100101 A
1J
b11010010100111011100010111011111 I
#25000
0!
b0 O
0"
0K
0&
b11110110100010011010010010100101 )
b11110110100010011010010010100101 P
1*
1Q
b1111100101100011 /
b1111100101100011 7
b1111100101100011 ?
b1111100101100011 G
b1111100101100011 '
00
08
0@
0H
0(
06
0>
0F
0N
0.
b10001100011011101001000000110111 5
b10001100011011101001000000110111 =
b10001100011011101001000000110111 E
b10001100011011101001000000110111 M
b10001100011011101001000000110111 -
12
b11110110100010011010010010100101 1
14
1:
b10101010111100001100010110001 9
1<
b100001011010011101111110000010 A
1D
0J
b1100110110111010111011110010100 I
#26000
b10110111101000101000111000001010 )
b10110111101000101000111000001010 P
0*
0Q
b1010110110110011 /
b1010110110110011 7
b1010110110110011 ?
b1010110110110011 G
b1010110110110011 '
0+
b110110101010011000110101110100 5
b110110101010011000110101110100 =
b110110101010011000110101110100 E
b110110101010011000110101110100 M
b110110101010011000110101110100 -
02
b10110111101000101000111000001010 1
0:
b11111010111100010101000000011011 9
b10000111010000011010111010010001 A
b110000110000011111101101101010 I
0L
#27000
b10110000010001000010100001001010 )
b10110000010001000010100001001010 P
b1001101110111101 /
b1001101110111101 7
b1001101110111101 ?
b1001101110111101 G
b1001101110111101 '
1+
16
1>
1F
1N
1.
b1001101011010110010001101001111 5
b1001101011010110010001101001111 =
b1001101011010110010001101001111 E
b1001101011010110010001101001111 M
b1001101011010110010001101001111 -
b10110000010001000010100001001010 1
b11001101001010111000100011011 9
0<
b11101100001110101010001100010100 A
0D
1J
b10100110100110000110110111100 I
#28000
1*
1Q
b10 O
1"
1C
1%
1,
1R
b10100110100110011011101011100000 )
b10100110100110011011101011100000 P
b100011001010011 /
b100011001010011 7
b100011001010011 ?
b100011001010011 G
b100011001010011 '
b11001010110101101110010100010100 5
b11001010110101101110010100010100 =
b11001010110101101110010100010100 E
b11001010110101101110010100010100 M
b11001010110101101110010100010100 -
b11011100100000100001010100100111 1
04
b10100111010100000010101010000001 9
1<
b10100110100110011011101011100000 A
1D
0J
b11101011101111100111001000000 I
1L
#29000
0*
0Q
b0 O
0"
0%
0C
b110100101010110001100011111101 )
b110100101010110001100011111101 P
b10011110001001 /
b10011110001001 7
b10011110001001 ?
b10011110001001 G
b10011110001001 '
0+
10
18
1@
1H
1(
06
0>
0F
0N
0.
b1010110101000000010000010101 5
b1010110101000000010000010101 =
b1010110101000000010000010101 E
b1010110101000000010000010101 M
b1010110101000000010000010101 -
b110100101010110001100011111101 1
14
b10001110111100000110011011010100 9
0<
b1011101111011001100000001101010 A
1J
b11101000111011000000000110110011 I
#30000
13
1#
0,
0R
b10100111110001011100101110000111 )
b10100111110001011100101110000111 P
1*
1Q
b101011000000 /
b101011000000 7
b101011000000 ?
b101011000000 G
b101011000000 '
1+
16
1>
1F
1N
1.
b10110011100010100000010111111011 5
b10110011100010100000010111111011 =
b10110011100010100000010111111011 E
b10110011100010100000010111111011 M
b10110011100010100000010111111011 -
12
b10100111110001011100101110000111 1
04
1:
b10100100111001101001010111001001 9
1<
0B
b10100011111000000100101100111011 A
0D
0J
b11011111000101001100011000010010 I
#31000
0#
03
b100011011100011110101000101100 )
b100011011100011110101000101100 P
0*
0Q
b10110110100100 /
b10110110100100 7
b10110110100100 ?
b10110110100100 G
b10110110100100 '
0+
00
08
0@
0H
0(
b1001010100000010100110101010011 5
b1001010100000010100110101010011 =
b1001010100000010100110101010011 E
b1001010100000010100110101010011 M
b1001010100000010100110101010011 -
02
b100011011100011110101000101100 1
0:
b1010101010110100100000010000101 9
0<
1B
b1011110000000001110101001101101 A
1D
b1010110100101111111000101111100 I
#32000
1,
1R
b11111011010111101011100001100110 )
b11111011010111101011100001100110 P
b1001111011011011 /
b1001111011011011 7
b1001111011011011 ?
b1001111011011011 G
b1001111011011011 '
06
0>
0F
0N
0.
b101001111100101100001111000111 5
b101001111100101100001111000111 =
b101001111100101100001111000111 E
b101001111100101100001111000111 M
b101001111100101100001111000111 -
b11111011010111101011100001100110 1
14
b1011100011001000110000000110110 9
b10001100011010010111011110001111 A
0D
b11101011010011101100111111100 I
0L
#33000
b11011011011001101011111111011010 )
b11011011011001101011111111011010 P
b1011101100000011 /
b1011101100000011 7
b1011101100000011 ?
b1011101100000011 G
b1011101100000011 '
10
18
1@
1H
1(
b1001110110100010011010101010011 5
b1001110110100010011010101010011 =
b1001110110100010011010101010011 E
b1001110110100010011010101010011 M
b1001110110100010011010101010011 -
b11011011011001101011111111011010 1
1:
b10010001001000001000111100110 9
0B
b11010101111001110011111000111111 A
b1101010001010110011001000000000 I
#34000
0,
0R
1*
1Q
b1 O
1!
1;
1$
b11001111111101001100010101101011 )
b11001111111101001100010101101011 P
b1100101110010 /
b1100101110010 7
b1100101110010 ?
b1100101110010 G
b1100101110010 '
1+
b1111001010110000101111001101001 5
b1111001010110000101111001101001 =
b1111001010110000101111001101001 E
b1111001010110000101111001101001 M
b1111001010110000101111001101001 -
b11010111010000011101011000001001 1
b11001111111101001100010101101011 9
b1111010101001010110101000011000 A
1J
b1111111011010111000011110010011 I
#35000
b0 O
0!
1#
0$
0;
1,
1R
b100111110110011001101000100011 )
b100111110110011001101000100011 P
1*
1Q
b100110101110 /
b100110101110 7
b100110101110 ?
b100110101110 G
b100110101110 '
0+
00
08
0@
0H
0(
16
1>
1F
1N
1.
b10101111111001100111100100001010 5
b10101111111001100111100100001010 =
b10101111111001100111100100001010 E
b10101111111001100111100100001010 M
b10101111111001100111100100001010 -
12
b100111110110011001101000100011 1
0:
b10100000011100100010101010100000 9
1<
b11001110010111011100100000000111 A
1D
b10100011100011011000101011111100 I
#36000
b1 O
1!
1;
0#
1$
03
0,
0R
b11001000110111000101011011111 )
b11001000110111000101011011111 P
0*
0Q
b1000011011010 /
b1000011011010 7
b1000011011010 ?
b1000011011010 G
b1000011011010 '
1+
06
0>
0F
0N
0.
b10111111111101110111001111001110 5
b10111111111101110111001111001110 =
b10111111111101110111001111001110 E
b10111111111101110111001111001110 M
b10111111111101110111001111001110 -
02
b1111101001111110111000000101 1
04
b11001000110111000101011011111 9
0<
1B
b10000100110111010110110110100110 A
0D
0J
b11101011100011110010000001010110 I
#37000
b0 O
0!
0;
0$
0,
0R
b10101011010101111010001011000 )
b10101011010101111010001011000 P
b1100100111001101 /
b1100100111001101 7
b1100100111001101 ?
b1100100111001101 G
b1100100111001101 '
10
18
1@
1H
1(
16
1>
1F
1N
1.
b110111100111011110110110100001 5
b110111100111011110110110100001 =
b110111100111011110110110100001 E
b110111100111011110110110100001 M
b110111100111011110110110100001 -
b10101011010101111010001011000 1
b11111101000010111010011100001110 9
1<
0B
b10010101110100011000000001010001 A
1D
b1101110011001001000000001000011 I
#38000
b10 O
1"
1%
b10101101010010101011000101010101 )
b10101101010010101011000101010101 P
1*
1Q
b101101111000111 /
b101101111000111 7
b101101111000111 ?
b101101111000111 G
b101101111000111 '
0+
00
08
0@
0H
0(
b11011101000100111000001001100110 5
b11011101000100111000001001100110 =
b11011101000100111000001001100110 E
b11011101000100111000001001100110 M
b11011101000100111000001001100110 -
12
b10110011101101101000101101010111 1
1:
b10000110100110111101101111010010 9
0<
1B
b10101101010010101011000101010101 A
0D
b1111111010000010001111111101101 I
#39000
b1110101010110100011101011000001 )
b1110101010110100011101011000001 P
0*
0Q
b100000110101000 /
b100000110101000 7
b100000110101000 ?
b100000110101000 G
b100000110101000 '
10
18
1@
1H
1(
06
0>
0F
0N
0.
b11111111001111100000101110100001 5
b11111111001111100000101110100001 =
b11111111001111100000101110100001 E
b11111111001111100000101110100001 M
b11111111001111100000101110100001 -
b11001100001001001001010101011000 1
b100101011101110111110011110000 9
0B
b1110101010110100011101011000001 A
b10001011111000000100110000111110 I
1L
#40000
b0 O
0"
0%
1,
1R
b100101111111011010110010111110 )
b100101111111011010110010111110 P
b10011010111101 /
b10011010111101 7
b10011010111101 ?
b10011010111101 G
b10011010111101 '
16
1>
1F
1N
1.
b11111011101001010010111001011001 5
b11111011101001010010111001011001 =
b11111011101001010010111001011001 E
b11111011101001010010111001011001 M
b11111011101001010010111001011001 -
02
b100101111111011010110010111110 1
14
0:
b10100011011010111100101100000001 9
1<
b11100000101011100001101000011011 A
1D
b10101101111001111100111011110011 I
#41000
b10100010100100111001101100111011 )
b10100010100100111001101100111011 P
b1110001101000101 /
b1110001101000101 7
b1110001101000101 ?
b1110001101000101 G
b1110001101000101 '
06
0>
0F
0N
0.
b11111111100010001110110010000010 5
b11111111100010001110110010000010 =
b11111111100010001110110010000010 E
b11111111100010001110110010000010 M
b11111111100010001110110010000010 -
b10100010100100111001101100111011 1
1:
b110011101101011011001111001110 9
1B
b11101110011010101000111000101111 A
0D
b1010111000110001010110110100010 I
