waves/Apb3Timer/rtl/Apb3Timer.v
// Generator : SpinalHDL v1.6.4    git head : 598c18959149eb18e5eee5b0aa3eef01ecaa41a1
// Component : Apb3Timer
// Git hash  : 89d7543c7219f82d1991c9174f1b313aba4435ca

`timescale 1ns/1ps 

module Apb3Timer (
  input      [7:0]    io_apb_PADDR,
  input      [0:0]    io_apb_PSEL,
  input               io_apb_PENABLE,
  output              io_apb_PREADY,
  input               io_apb_PWRITE,
  input      [31:0]   io_apb_PWDATA,
  output reg [31:0]   io_apb_PRDATA,
  output              io_apb_PSLVERROR,
  output              io_fullA,
  output              io_fullB,
  input               io_external_tick,
  input               io_external_clear,
  input               clk,
  input               reset
);

  wire                timerA_io_tick;
  wire                timerA_io_clear;
  wire                timerB_io_tick;
  wire                timerB_io_clear;
  wire                timerA_io_full;
  wire       [15:0]   timerA_io_value;
  wire                timerB_io_full;
  wire       [7:0]    timerB_io_value;
  reg        [3:0]    clockDivider_counter;
  wire                clockDivider_full;
  wire                apbCtrl_askWrite;
  wire                apbCtrl_askRead;
  wire                apbCtrl_doWrite;
  wire                apbCtrl_doRead;
  reg        [2:0]    bridgeA_ticksEnable;
  reg        [1:0]    bridgeA_clearsEnable;
  reg                 bridgeA_busClear;
  reg        [15:0]   timerA_io_limit_driver;
  reg                 when_Timer_l39;
  reg                 when_Timer_l42;
  reg        [2:0]    bridgeB_ticksEnable;
  reg        [1:0]    bridgeB_clearsEnable;
  reg                 bridgeB_busClear;
  reg        [7:0]    timerB_io_limit_driver;
  reg                 when_Timer_l39_1;
  reg                 when_Timer_l42_1;

  Timer timerA (
    .io_tick     (timerA_io_tick                ), //i
    .io_clear    (timerA_io_clear               ), //i
    .io_limit    (timerA_io_limit_driver[15:0]  ), //i
    .io_full     (timerA_io_full                ), //o
    .io_value    (timerA_io_value[15:0]         ), //o
    .clk         (clk                           ), //i
    .reset       (reset                         )  //i
  );
  Timer_1 timerB (
    .io_tick     (timerB_io_tick               ), //i
    .io_clear    (timerB_io_clear              ), //i
    .io_limit    (timerB_io_limit_driver[7:0]  ), //i
    .io_full     (timerB_io_full               ), //o
    .io_value    (timerB_io_value[7:0]         ), //o
    .clk         (clk                          ), //i
    .reset       (reset                        )  //i
  );
  assign clockDivider_full = (clockDivider_counter == 4'b1111);
  assign io_apb_PREADY = 1'b1;
  always @(*) begin
    io_apb_PRDATA = 32'h0;
    case(io_apb_PADDR)
      8'h0 : begin
        io_apb_PRDATA[2 : 0] = bridgeA_ticksEnable;
        io_apb_PRDATA[17 : 16] = bridgeA_clearsEnable;
      end
      8'h04 : begin
        io_apb_PRDATA[15 : 0] = timerA_io_limit_driver;
      end
      8'h08 : begin
        io_apb_PRDATA[15 : 0] = timerA_io_value;
      end
      8'h10 : begin
        io_apb_PRDATA[2 : 0] = bridgeB_ticksEnable;
        io_apb_PRDATA[17 : 16] = bridgeB_clearsEnable;
      end
      8'h14 : begin
        io_apb_PRDATA[7 : 0] = timerB_io_limit_driver;
      end
      8'h18 : begin
        io_apb_PRDATA[7 : 0] = timerB_io_value;
      end
      default : begin
      end
    endcase
  end

  assign io_apb_PSLVERROR = 1'b0;
  assign apbCtrl_askWrite = ((io_apb_PSEL[0] && io_apb_PENABLE) && io_apb_PWRITE);
  assign apbCtrl_askRead = ((io_apb_PSEL[0] && io_apb_PENABLE) && (! io_apb_PWRITE));
  assign apbCtrl_doWrite = (((io_apb_PSEL[0] && io_apb_PENABLE) && io_apb_PREADY) && io_apb_PWRITE);
  assign apbCtrl_doRead = (((io_apb_PSEL[0] && io_apb_PENABLE) && io_apb_PREADY) && (! io_apb_PWRITE));
  always @(*) begin
    bridgeA_busClear = 1'b0;
    if(when_Timer_l39) begin
      bridgeA_busClear = 1'b1;
    end
    if(when_Timer_l42) begin
      bridgeA_busClear = 1'b1;
    end
  end

  assign timerA_io_clear = ((|({io_external_clear,timerA_io_full} & bridgeA_clearsEnable)) || bridgeA_busClear);
  assign timerA_io_tick = (|({io_external_tick,{clockDivider_full,1'b1}} & bridgeA_ticksEnable));
  always @(*) begin
    when_Timer_l39 = 1'b0;
    case(io_apb_PADDR)
      8'h04 : begin
        if(apbCtrl_doWrite) begin
          when_Timer_l39 = 1'b1;
        end
      end
      default : begin
      end
    endcase
  end

  always @(*) begin
    when_Timer_l42 = 1'b0;
    case(io_apb_PADDR)
      8'h08 : begin
        if(apbCtrl_doWrite) begin
          when_Timer_l42 = 1'b1;
        end
      end
      default : begin
      end
    endcase
  end

  always @(*) begin
    bridgeB_busClear = 1'b0;
    if(when_Timer_l39_1) begin
      bridgeB_busClear = 1'b1;
    end
    if(when_Timer_l42_1) begin
      bridgeB_busClear = 1'b1;
    end
  end

  assign timerB_io_clear = ((|({io_external_clear,timerB_io_full} & bridgeB_clearsEnable)) || bridgeB_busClear);
  assign timerB_io_tick = (|({io_external_tick,{clockDivider_full,1'b1}} & bridgeB_ticksEnable));
  always @(*) begin
    when_Timer_l39_1 = 1'b0;
    case(io_apb_PADDR)
      8'h14 : begin
        if(apbCtrl_doWrite) begin
          when_Timer_l39_1 = 1'b1;
        end
      end
      default : begin
      end
    endcase
  end

  always @(*) begin
    when_Timer_l42_1 = 1'b0;
    case(io_apb_PADDR)
      8'h18 : begin
        if(apbCtrl_doWrite) begin
          when_Timer_l42_1 = 1'b1;
        end
      end
      default : begin
      end
    endcase
  end

  assign io_fullA = timerA_io_full;
  assign io_fullB = timerB_io_full;
  always @(posedge clk or posedge reset) begin
    if(reset) begin
      clockDivider_counter <= 4'b0000;
      bridgeA_ticksEnable <= 3'b000;
      bridgeA_clearsEnable <= 2'b00;
      bridgeB_ticksEnable <= 3'b000;
      bridgeB_clearsEnable <= 2'b00;
    end else begin
      clockDivider_counter <= (clockDivider_counter + 4'b0001);
      case(io_apb_PADDR)
        8'h0 : begin
          if(apbCtrl_doWrite) begin
            bridgeA_ticksEnable <= io_apb_PWDATA[2 : 0];
            bridgeA_clearsEnable <= io_apb_PWDATA[17 : 16];
          end
        end
        8'h10 : begin
          if(apbCtrl_doWrite) begin
            bridgeB_ticksEnable <= io_apb_PWDATA[2 : 0];
            bridgeB_clearsEnable <= io_apb_PWDATA[17 : 16];
          end
        end
        default : begin
        end
      endcase
    end
  end

  always @(posedge clk) begin
    case(io_apb_PADDR)
      8'h04 : begin
        if(apbCtrl_doWrite) begin
          timerA_io_limit_driver <= io_apb_PWDATA[15 : 0];
        end
      end
      8'h14 : begin
        if(apbCtrl_doWrite) begin
          timerB_io_limit_driver <= io_apb_PWDATA[7 : 0];
        end
      end
      default : begin
      end
    endcase
  end


endmodule

module Timer_1 (
  input               io_tick,
  input               io_clear,
  input      [7:0]    io_limit,
  output              io_full,
  output     [7:0]    io_value,
  input               clk,
  input               reset
);

  reg        [7:0]    counter;
  wire                when_Timer_l20;

  assign when_Timer_l20 = (io_tick && (! io_full));
  assign io_full = (counter == io_limit);
  assign io_value = counter;
  always @(posedge clk or posedge reset) begin
    if(reset) begin
      counter <= 8'h0;
    end else begin
      if(when_Timer_l20) begin
        counter <= (counter + 8'h01);
      end
      if(io_clear) begin
        counter <= 8'h0;
      end
    end
  end


endmodule

module Timer (
  input               io_tick,
  input               io_clear,
  input      [15:0]   io_limit,
  output              io_full,
  output     [15:0]   io_value,
  input               clk,
  input               reset
);

  reg        [15:0]   counter;
  wire                when_Timer_l20;

  assign when_Timer_l20 = (io_tick && (! io_full));
  assign io_full = (counter == io_limit);
  assign io_value = counter;
  always @(posedge clk or posedge reset) begin
    if(reset) begin
      counter <= 16'h0;
    end else begin
      if(when_Timer_l20) begin
        counter <= (counter + 16'h0001);
      end
      if(io_clear) begin
        counter <= 16'h0;
      end
    end
  end


endmodule

waves/Apb3Timer/test.vcd
$version Generated by VerilatedVcd $end
$date mar. 12 avril 2022 13:11:59 $end
$timescale 1ps $end

 $scope module TOP $end
  $var wire  1 > clk $end
  $var wire  8 2 io_apb_PADDR [7:0] $end
  $var wire  1 4 io_apb_PENABLE $end
  $var wire 32 8 io_apb_PRDATA [31:0] $end
  $var wire  1 5 io_apb_PREADY $end
  $var wire  1 3 io_apb_PSEL [0:0] $end
  $var wire  1 9 io_apb_PSLVERROR $end
  $var wire 32 7 io_apb_PWDATA [31:0] $end
  $var wire  1 6 io_apb_PWRITE $end
  $var wire  1 = io_external_clear $end
  $var wire  1 < io_external_tick $end
  $var wire  1 : io_fullA $end
  $var wire  1 ; io_fullB $end
  $var wire  1 ? reset $end
  $scope module Apb3Timer $end
   $var wire  1 G apbCtrl_askRead $end
   $var wire  1 F apbCtrl_askWrite $end
   $var wire  1 G apbCtrl_doRead $end
   $var wire  1 + apbCtrl_doWrite $end
   $var wire  1 , bridgeA_busClear $end
   $var wire  2 ( bridgeA_clearsEnable [1:0] $end
   $var wire  3 ' bridgeA_ticksEnable [2:0] $end
   $var wire  1 / bridgeB_busClear $end
   $var wire  2 * bridgeB_clearsEnable [1:0] $end
   $var wire  3 ) bridgeB_ticksEnable [2:0] $end
   $var wire  1 > clk $end
   $var wire  4 % clockDivider_counter [3:0] $end
   $var wire  1 & clockDivider_full $end
   $var wire  8 2 io_apb_PADDR [7:0] $end
   $var wire  1 4 io_apb_PENABLE $end
   $var wire 32 8 io_apb_PRDATA [31:0] $end
   $var wire  1 5 io_apb_PREADY $end
   $var wire  1 3 io_apb_PSEL [0:0] $end
   $var wire  1 9 io_apb_PSLVERROR $end
   $var wire 32 7 io_apb_PWDATA [31:0] $end
   $var wire  1 6 io_apb_PWRITE $end
   $var wire  1 = io_external_clear $end
   $var wire  1 < io_external_tick $end
   $var wire  1 : io_fullA $end
   $var wire  1 ; io_fullB $end
   $var wire  1 ? reset $end
   $var wire  1 A timerA_io_clear $end
   $var wire  1 D timerA_io_full $end
   $var wire 16 H timerA_io_limit_driver [15:0] $end
   $var wire  1 @ timerA_io_tick $end
   $var wire 16 # timerA_io_value [15:0] $end
   $var wire  1 C timerB_io_clear $end
   $var wire  1 E timerB_io_full $end
   $var wire  8 I timerB_io_limit_driver [7:0] $end
   $var wire  1 B timerB_io_tick $end
   $var wire  8 $ timerB_io_value [7:0] $end
   $var wire  1 - when_Timer_l39 $end
   $var wire  1 0 when_Timer_l39_1 $end
   $var wire  1 . when_Timer_l42 $end
   $var wire  1 1 when_Timer_l42_1 $end
   $scope module timerA $end
    $var wire  1 > clk $end
    $var wire 16 # counter [15:0] $end
    $var wire  1 A io_clear $end
    $var wire  1 D io_full $end
    $var wire 16 H io_limit [15:0] $end
    $var wire  1 @ io_tick $end
    $var wire 16 # io_value [15:0] $end
    $var wire  1 ? reset $end
    $var wire  1 J when_Timer_l20 $end
   $upscope $end
   $scope module timerB $end
    $var wire  1 > clk $end
    $var wire  8 $ counter [7:0] $end
    $var wire  1 C io_clear $end
    $var wire  1 E io_full $end
    $var wire  8 I io_limit [7:0] $end
    $var wire  1 B io_tick $end
    $var wire  8 $ io_value [7:0] $end
    $var wire  1 ? reset $end
    $var wire  1 K when_Timer_l20 $end
   $upscope $end
  $upscope $end
 $upscope $end
$enddefinitions $end


#0
b0000000000000000 #
b00000000 $
b0000 %
0&
b000 '
b00 (
b000 )
b00 *
0+
0,
0-
0.
0/
00
01
b01111110 2
03
04
15
16
b10111101001001001100001010010110 7
b00000000000000000000000000000000 8
09
0:
0;
0<
0=
0>
1?
0@
0A
0B
0C
0D
0E
0F
0G
b1101000100000101 H
b01111111 I
0J
0K
#160
0?
#170
b0001 %
b00001000 2
13
b00000000000000000000000000000000 7
1>
#175
0>
#180
b0010 %
1+
1,
1.
14
1>
1A
1F
#185
0>
#190
b0011 %
0+
0,
0.
04
06
b01110100010100000110010010100101 7
1>
0A
0F
#195
0>
#200
b0100 %
14
1>
1G
#205
0>
#210
b0101 %
b00000100 2
04
16
b00000000000000000000000000111111 7
b00000000000000001101000100000101 8
1>
0G
#215
0>
#220
b0110 %
1+
1,
1-
14
1>
1A
1F
#225
0>
#230
b0111 %
0+
0,
0-
04
06
b10101101110000100111011100100100 7
b00000000000000000000000000111111 8
1>
0A
0F
b0000000000111111 H
#235
0>
#240
b1000 %
14
1>
1G
#245
0>
#250
b1001 %
04
16
b00000000000000000000000000011111 7
1>
0G
#255
0>
#260
b1010 %
1+
1,
1-
14
1>
1A
1F
#265
0>
#270
b1011 %
0+
0,
0-
04
06
b10000101010010110001101101101100 7
b00000000000000000000000000011111 8
1>
0A
0F
b0000000000011111 H
#275
0>
#280
b1100 %
14
1>
1G
#285
0>
#290
b1101 %
b00000000 2
04
16
b00000000000000000000000000000001 7
b00000000000000000000000000000000 8
1>
0G
#295
0>
#300
b1110 %
1+
14
1>
1F
#305
0>
#310
b1111 %
1&
b001 '
0+
b10111100 2
03
04
06
b00100010011110001100111010011100 7
1>
1@
0F
1J
#315
0>
#320
b0000000000000001 #
b0000 %
0&
1>
#325
0>
#330
b0000000000000010 #
b0001 %
1>
#335
0>
#340
b0000000000000011 #
b0010 %
1>
#345
0>
#350
b0000000000000100 #
b0011 %
1>
#355
0>
#360
b0000000000000101 #
b0100 %
1>
#365
0>
#370
b0000000000000110 #
b0101 %
1>
#375
0>
#380
b0000000000000111 #
b0110 %
1>
#385
0>
#390
b0000000000001000 #
b0111 %
1>
#395
0>
#400
b0000000000001001 #
b1000 %
1>
#405
0>
#410
b0000000000001010 #
b1001 %
1>
#415
0>
#420
b0000000000001011 #
b1010 %
1>
#425
0>
#430
b0000000000001100 #
b1011 %
1>
#435
0>
#440
b0000000000001101 #
b1100 %
1>
#445
0>
#450
b0000000000001110 #
b1101 %
1>
#455
0>
#460
b0000000000001111 #
b1110 %
1>
#465
0>
#470
b0000000000010000 #
b1111 %
1&
1>
#475
0>
#480
b0000000000010001 #
b0000 %
0&
1>
#485
0>
#490
b0000000000010010 #
b0001 %
1>
#495
0>
#500
b0000000000010011 #
b0010 %
1>
#505
0>
#510
b0000000000010100 #
b0011 %
1>
#515
0>
#520
b0000000000010101 #
b0100 %
1>
#525
0>
#530
b0000000000010110 #
b0101 %
1>
#535
0>
#540
b0000000000010111 #
b0110 %
1>
#545
0>
#550
b0000000000011000 #
b0111 %
1>
#555
0>
#560
b0000000000011001 #
b1000 %
1>
#565
0>
#570
b0000000000011010 #
b1001 %
1>
#575
0>
#580
b0000000000011011 #
b1010 %
1>
#585
0>
#590
b0000000000011100 #
b1011 %
1>
#595
0>
#600
b0000000000011101 #
b1100 %
1>
#605
0>
#610
b0000000000011110 #
b1101 %
1>
#615
0>
#620
b0000000000011111 #
b1110 %
1:
1>
1D
0J
#625
0>
#630
b1111 %
1&
1>
#635
0>
#640
b0000 %
0&
1>
#645
0>
#650
b0001 %
b00000100 2
13
16
b00000000000000000000000000101111 7
b00000000000000000000000000011111 8
1>
#655
0>
#660
b0010 %
1+
1,
1-
14
1>
1A
1F
#665
0>
#670
b0000000000000000 #
b0011 %
0+
0,
0-
b00111101 2
03
06
b00011110010100001111001111000100 7
b00000000000000000000000000000000 8
0:
1>
0A
0D
0F
b0000000000101111 H
1J
#675
0>
#680
b0000000000000001 #
b0100 %
1>
#685
0>
#690
b0000000000000010 #
b0101 %
1>
#695
0>
#700
b0000000000000011 #
b0110 %
1>
#705
0>
#710
b0000000000000100 #
b0111 %
1>
#715
0>
#720
b0000000000000101 #
b1000 %
1>
#725
0>
#730
b0000000000000110 #
b1001 %
1>
#735
0>
#740
b0000000000000111 #
b1010 %
1>
#745
0>
#750
b0000000000001000 #
b1011 %
1>
#755
0>
#760
b0000000000001001 #
b1100 %
1>
#765
0>
#770
b0000000000001010 #
b1101 %
1>
#775
0>
#780
b0000000000001011 #
b1110 %
1>
#785
0>
#790
b0000000000001100 #
b1111 %
1&
1>
#795
0>
#800
b0000000000001101 #
b0000 %
0&
1>
#805
0>
#810
b0000000000001110 #
b0001 %
1>
#815
0>
#820
b0000000000001111 #
b0010 %
1>
#825
0>
#830
b0000000000010000 #
b0011 %
1>
#835
0>
#840
b0000000000010001 #
b0100 %
1>
#845
0>
#850
b0000000000010010 #
b0101 %
1>
#855
0>
#860
b0000000000010011 #
b0110 %
1>
#865
0>
#870
b0000000000010100 #
b0111 %
1>
#875
0>
#880
b0000000000010101 #
b1000 %
1>
#885
0>
#890
b0000000000010110 #
b1001 %
1>
#895
0>
#900
b0000000000010111 #
b1010 %
1>
#905
0>
#910
b0000000000011000 #
b1011 %
1>
#915
0>
#920
b0000000000011001 #
b1100 %
1>
#925
0>
#930
b0000000000011010 #
b1101 %
1>
#935
0>
#940
b0000000000011011 #
b1110 %
1>
#945
0>
#950
b0000000000011100 #
b1111 %
1&
1>
#955
0>
#960
b0000000000011101 #
b0000 %
0&
1>
#965
0>
#970
b0000000000011110 #
b0001 %
1>
#975
0>
#980
b0000000000011111 #
b0010 %
1>
#985
0>
#990
b0000000000100000 #
b0011 %
1>
#995
0>
#1000
b0000000000100001 #
b0100 %
1>
#1005
0>
#1010
b0000000000100010 #
b0101 %
1>
#1015
0>
#1020
b0000000000100011 #
b0110 %
1>
#1025
0>
#1030
b0000000000100100 #
b0111 %
1>
#1035
0>
#1040
b0000000000100101 #
b1000 %
1>
#1045
0>
#1050
b0000000000100110 #
b1001 %
1>
#1055
0>
#1060
b0000000000100111 #
b1010 %
1>
#1065
0>
#1070
b0000000000101000 #
b1011 %
1>
#1075
0>
#1080
b0000000000101001 #
b1100 %
1>
#1085
0>
#1090
b0000000000101010 #
b1101 %
1>
#1095
0>
#1100
b0000000000101011 #
b1110 %
1>
#1105
0>
#1110
b0000000000101100 #
b1111 %
1&
1>
#1115
0>
#1120
b0000000000101101 #
b0000 %
0&
1>
#1125
0>
#1130
b0000000000101110 #
b0001 %
1>
#1135
0>
#1140
b0000000000101111 #
b0010 %
1:
1>
1D
0J
#1145
0>
#1150
b0011 %
b00000100 2
13
04
16
b00000000000000000000000000011111 7
b00000000000000000000000000101111 8
1>
#1155
0>
#1160
b0100 %
1+
1,
1-
14
1>
1A
1F
#1165
0>
#1170
b0000000000000000 #
b0101 %
0+
0,
0-
b00000000 2
04
b00000000000000010000000000000001 7
b00000000000000000000000000000001 8
0:
1>
0A
0D
0F
b0000000000011111 H
1J
#1175
0>
#1180
b0000000000000001 #
b0110 %
1+
14
1>
1F
#1185
0>
#1190
b0000000000000010 #
b0111 %
b01 (
0+
b00001000 2
04
b00000000000000000000000000000000 7
b00000000000000000000000000000010 8
1>
0F
#1195
0>
#1200
b0000000000000011 #
b1000 %
1+
1,
1.
14
b00000000000000000000000000000011 8
1>
1A
1F
#1205
0>
#1210
b0000000000000000 #
b1001 %
0+
0,
0.
b01101001 2
03
04
b10010011110111110001110011111010 7
b00000000000000000000000000000000 8
1>
0A
0F
#1215
0>
#1220
b0000000000000001 #
b1010 %
1>
#1225
0>
#1230
b0000000000000010 #
b1011 %
1>
#1235
0>
#1240
b0000000000000011 #
b1100 %
1>
#1245
0>
#1250
b0000000000000100 #
b1101 %
1>
#1255
0>
#1260
b0000000000000101 #
b1110 %
1>
#1265
0>
#1270
b0000000000000110 #
b1111 %
1&
1>
#1275
0>
#1280
b0000000000000111 #
b0000 %
0&
1>
#1285
0>
#1290
b0000000000001000 #
b0001 %
1>
#1295
0>
#1300
b0000000000001001 #
b0010 %
1>
#1305
0>
#1310
b0000000000001010 #
b0011 %
1>
#1315
0>
#1320
b0000000000001011 #
b0100 %
1>
#1325
0>
#1330
b0000000000001100 #
b0101 %
1>
#1335
0>
#1340
b0000000000001101 #
b0110 %
1>
#1345
0>
#1350
b0000000000001110 #
b0111 %
1>
#1355
0>
#1360
b0000000000001111 #
b1000 %
1>
#1365
0>
#1370
b0000000000010000 #
b1001 %
1>
#1375
0>
#1380
b0000000000010001 #
b1010 %
1>
#1385
0>
#1390
b0000000000010010 #
b1011 %
1>
#1395
0>
#1400
b0000000000010011 #
b1100 %
1>
#1405
0>
#1410
b0000000000010100 #
b1101 %
1>
#1415
0>
#1420
b0000000000010101 #
b1110 %
1>
#1425
0>
#1430
b0000000000010110 #
b1111 %
1&
1>
#1435
0>
#1440
b0000000000010111 #
b0000 %
0&
1>
#1445
0>
#1450
b0000000000011000 #
b0001 %
1>
#1455
0>
#1460
b0000000000011001 #
b0010 %
1>
#1465
0>
#1470
b0000000000011010 #
b0011 %
1>
#1475
0>
#1480
b0000000000011011 #
b0100 %
1>
#1485
0>
#1490
b0000000000011100 #
b0101 %
1>
#1495
0>
#1500
b0000000000011101 #
b0110 %
1>
#1505
0>
#1510
b0000000000011110 #
b0111 %
1>
#1515
0>
#1520
b0000000000011111 #
b1000 %
1:
1>
1A
1D
0J
#1525
0>
#1530
b0000000000000000 #
b1001 %
0:
1>
0A
0D
1J
#1535
0>
#1540
b0000000000000001 #
b1010 %
1>
#1545
0>
#1550
b0000000000000010 #
b1011 %
1>
#1555
0>
#1560
b0000000000000011 #
b1100 %
1>
#1565
0>
#1570
b0000000000000100 #
b1101 %
1>
#1575
0>
#1580
b0000000000000101 #
b1110 %
1>
#1585
0>
#1590
b0000000000000110 #
b1111 %
1&
1>
#1595
0>
#1600
b0000000000000111 #
b0000 %
0&
1>
#1605
0>
#1610
b0000000000001000 #
b0001 %
1>
#1615
0>
#1620
b0000000000001001 #
b0010 %
1>
#1625
0>
#1630
b0000000000001010 #
b0011 %
1>
#1635
0>
#1640
b0000000000001011 #
b0100 %
1>
#1645
0>
#1650
b0000000000001100 #
b0101 %
1>
#1655
0>
#1660
b0000000000001101 #
b0110 %
1>
#1665
0>
#1670
b0000000000001110 #
b0111 %
1>
#1675
0>
#1680
b0000000000001111 #
b1000 %
1>
#1685
0>
#1690
b0000000000010000 #
b1001 %
1>
#1695
0>
#1700
b0000000000010001 #
b1010 %
1>
#1705
0>
#1710
b0000000000010010 #
b1011 %
1>
#1715
0>
#1720
b0000000000010011 #
b1100 %
1>
#1725
0>
#1730
b0000000000010100 #
b1101 %
1>
#1735
0>
#1740
b0000000000010101 #
b1110 %
1>
#1745
0>
#1750
b0000000000010110 #
b1111 %
1&
1>
#1755
0>
#1760
b0000000000010111 #
b0000 %
0&
1>
#1765
0>
#1770
b0000000000011000 #
b0001 %
1>
#1775
0>
#1780
b0000000000011001 #
b0010 %
1>
#1785
0>
#1790
b0000000000011010 #
b0011 %
1>
#1795
0>
#1800
b0000000000011011 #
b0100 %
1>
#1805
0>
#1810
b0000000000011100 #
b0101 %
1>
#1815
0>
#1820
b0000000000011101 #
b0110 %
1>
#1825
0>
#1830
b0000000000011110 #
b0111 %
1>
#1835
0>
#1840
b0000000000011111 #
b1000 %
1:
1>
1A
1D
0J
#1845
0>
#1850
b0000000000000000 #
b1001 %
b00000000 2
13
b00000000000000010000000000000010 7
b00000000000000010000000000000001 8
0:
1>
0A
0D
1J
#1855
0>
#1860
b0000000000000001 #
b1010 %
1+
14
1>
1F
#1865
0>
#1870
b0000000000000010 #
b1011 %
b010 '
0+
b00001000 2
04
b00000000000000000000000000000000 7
b00000000000000000000000000000010 8
1>
0@
0F
0J
#1875
0>
#1880
b1100 %
1+
1,
1.
14
1>
1A
1F
#1885
0>
#1890
b0000000000000000 #
b1101 %
0+
0,
0.
b10011010 2
03
b01100011000001100110100011110100 7
b00000000000000000000000000000000 8
1>
0A
0F
#1895
0>
#1900
b1110 %
1>
#1905
0>
#1910
b1111 %
1&
1>
1@
1J
#1915
0>
#1920
b0000000000000001 #
b0000 %
0&
1>
0@
0J
#1925
0>
#1930
b0001 %
1>
#1935
0>
#1940
b0010 %
1>
#1945
0>
#1950
b0011 %
1>
#1955
0>
#1960
b0100 %
1>
#1965
0>
#1970
b0101 %
1>
#1975
0>
#1980
b0110 %
1>
#1985
0>
#1990
b0111 %
1>
#1995
0>
#2000
b1000 %
1>
#2005
0>
#2010
b1001 %
1>
#2015
0>
#2020
b1010 %
1>
#2025
0>
#2030
b1011 %
1>
#2035
0>
#2040
b1100 %
1>
#2045
0>
#2050
b1101 %
1>
#2055
0>
#2060
b1110 %
1>
#2065
0>
#2070
b1111 %
1&
1>
1@
1J
#2075
0>
#2080
b0000000000000010 #
b0000 %
0&
1>
0@
0J
#2085
0>
#2090
b0001 %
1>
#2095
0>
#2100
b0010 %
1>
#2105
0>
#2110
b0011 %
1>
#2115
0>
#2120
b0100 %
1>
#2125
0>
#2130
b0101 %
1>
#2135
0>
#2140
b0110 %
1>
#2145
0>
#2150
b0111 %
1>
#2155
0>
#2160
b1000 %
1>
#2165
0>
#2170
b1001 %
1>
#2175
0>
#2180
b1010 %
1>
#2185
0>
#2190
b1011 %
1>
#2195
0>
#2200
b1100 %
1>
#2205
0>
#2210
b1101 %
1>
#2215
0>
#2220
b1110 %
1>
#2225
0>
#2230
b1111 %
1&
1>
1@
1J
#2235
0>
#2240
b0000000000000011 #
b0000 %
0&
1>
0@
0J
#2245
0>
#2250
b0001 %
1>
#2255
0>
#2260
b0010 %
1>
#2265
0>
#2270
b0011 %
1>
#2275
0>
#2280
b0100 %
1>
#2285
0>
#2290
b0101 %
1>
#2295
0>
#2300
b0110 %
1>
#2305
0>
#2310
b0111 %
1>
#2315
0>
#2320
b1000 %
1>
#2325
0>
#2330
b1001 %
1>
#2335
0>
#2340
b1010 %
1>
#2345
0>
#2350
b1011 %
1>
#2355
0>
#2360
b1100 %
1>
#2365
0>
#2370
b1101 %
1>
#2375
0>
#2380
b1110 %
1>
#2385
0>
#2390
b1111 %
1&
1>
1@
1J
#2395
0>
#2400
b0000000000000100 #
b0000 %
0&
1>
0@
0J
#2405
0>
#2410
b0001 %
1>
#2415
0>
#2420
b0010 %
1>
#2425
0>
#2430
b0011 %
1>
#2435
0>
#2440
b0100 %
1>
#2445
0>
#2450
b0101 %
1>
#2455
0>
#2460
b0110 %
1>
#2465
0>
#2470
b0111 %
1>
#2475
0>
#2480
b1000 %
1>
#2485
0>
#2490
b1001 %
1>
#2495
0>
#2500
b1010 %
1>
#2505
0>
#2510
b1011 %
1>
#2515
0>
#2520
b1100 %
1>
#2525
0>
#2530
b1101 %
1>
#2535
0>
#2540
b1110 %
1>
#2545
0>
#2550
b1111 %
1&
1>
1@
1J
#2555
0>
#2560
b0000000000000101 #
b0000 %
0&
1>
0@
0J
#2565
0>
#2570
b0001 %
1>
#2575
0>
#2580
b0010 %
1>
#2585
0>
#2590
b0011 %
1>
#2595
0>
#2600
b0100 %
1>
#2605
0>
#2610
b0101 %
1>
#2615
0>
#2620
b0110 %
1>
#2625
0>
#2630
b0111 %
1>
#2635
0>
#2640
b1000 %
1>
#2645
0>
#2650
b1001 %
1>
#2655
0>
#2660
b1010 %
1>
#2665
0>
#2670
b1011 %
1>
#2675
0>
#2680
b1100 %
1>
#2685
0>
#2690
b1101 %
1>
#2695
0>
#2700
b1110 %
1>
#2705
0>
#2710
b1111 %
1&
1>
1@
1J
#2715
0>
#2720
b0000000000000110 #
b0000 %
0&
1>
0@
0J
#2725
0>
#2730
b0001 %
1>
#2735
0>
#2740
b0010 %
1>
#2745
0>
#2750
b0011 %
1>
#2755
0>
#2760
b0100 %
1>
#2765
0>
#2770
b0101 %
1>
#2775
0>
#2780
b0110 %
1>
#2785
0>
#2790
b0111 %
1>
#2795
0>
#2800
b1000 %
1>
#2805
0>
#2810
b1001 %
1>
#2815
0>
#2820
b1010 %
1>
#2825
0>
#2830
b1011 %
1>
#2835
0>
#2840
b1100 %
1>
#2845
0>
#2850
b1101 %
1>
#2855
0>
#2860
b1110 %
1>
#2865
0>
#2870
b1111 %
1&
1>
1@
1J
#2875
0>
#2880
b0000000000000111 #
b0000 %
0&
1>
0@
0J
#2885
0>
#2890
b0001 %
1>
#2895
0>
#2900
b0010 %
1>
#2905
0>
#2910
b0011 %
1>
#2915
0>
#2920
b0100 %
1>
#2925
0>
#2930
b0101 %
1>
#2935
0>
#2940
b0110 %
1>
#2945
0>
#2950
b0111 %
1>
#2955
0>
#2960
b1000 %
1>
#2965
0>
#2970
b1001 %
1>
#2975
0>
#2980
b1010 %
1>
#2985
0>
#2990
b1011 %
1>
#2995
0>
#3000
b1100 %
1>
#3005
0>
#3010
b1101 %
1>
#3015
0>
#3020
b1110 %
1>
#3025
0>
#3030
b1111 %
1&
1>
1@
1J
#3035
0>
#3040
b0000000000001000 #
b0000 %
0&
1>
0@
0J
#3045
0>
#3050
b0001 %
1>
#3055
0>
#3060
b0010 %
1>
#3065
0>
#3070
b0011 %
1>
#3075
0>
#3080
b0100 %
1>
#3085
0>
#3090
b0101 %
1>
#3095
0>
#3100
b0110 %
1>
#3105
0>
#3110
b0111 %
1>
#3115
0>
#3120
b1000 %
1>
#3125
0>
#3130
b1001 %
1>
#3135
0>
#3140
b1010 %
1>
#3145
0>
#3150
b1011 %
1>
#3155
0>
#3160
b1100 %
1>
#3165
0>
#3170
b1101 %
1>
#3175
0>
#3180
b1110 %
1>
#3185
0>
#3190
b1111 %
1&
1>
1@
1J
#3195
0>
#3200
b0000000000001001 #
b0000 %
0&
1>
0@
0J
#3205
0>
#3210
b0001 %
1>
#3215
0>
#3220
b0010 %
1>
#3225
0>
#3230
b0011 %
1>
#3235
0>
#3240
b0100 %
1>
#3245
0>
#3250
b0101 %
1>
#3255
0>
#3260
b0110 %
1>
#3265
0>
#3270
b0111 %
1>
#3275
0>
#3280
b1000 %
1>
#3285
0>
#3290
b1001 %
1>
#3295
0>
#3300
b1010 %
1>
#3305
0>
#3310
b1011 %
1>
#3315
0>
#3320
b1100 %
1>
#3325
0>
#3330
b1101 %
1>
#3335
0>
#3340
b1110 %
1>
#3345
0>
#3350
b1111 %
1&
1>
1@
1J
#3355
0>
#3360
b0000000000001010 #
b0000 %
0&
1>
0@
0J
#3365
0>
#3370
b0001 %
1>
#3375
0>
#3380
b0010 %
1>
#3385
0>
#3390
b0011 %
1>
#3395
0>
#3400
b0100 %
1>
#3405
0>
#3410
b0101 %
1>
#3415
0>
