waves/Timer/rtl/Timer.v
// Generator : SpinalHDL v1.6.4    git head : 598c18959149eb18e5eee5b0aa3eef01ecaa41a1
// Component : Timer
// Git hash  : 89d7543c7219f82d1991c9174f1b313aba4435ca

`timescale 1ns/1ps 

module Timer (
  input               io_tick,
  input               io_clear,
  input      [7:0]    io_limit,
  output              io_full,
  output     [7:0]    io_value,
  input               clk,
  input               reset
);

  reg        [7:0]    counter;
  wire                when_Timer_l20;

  assign when_Timer_l20 = (io_tick && (! io_full));
  assign io_full = (counter == io_limit);
  assign io_value = counter;
  always @(posedge clk or posedge reset) begin
    if(reset) begin
      counter <= 8'h0;
    end else begin
      if(when_Timer_l20) begin
        counter <= (counter + 8'h01);
      end
      if(io_clear) begin
        counter <= 8'h0;
      end
    end
  end


endmodule

waves/Timer/test.vcd
$version Generated by VerilatedVcd $end
$date mar. 12 avril 2022 13:04:38 $end
$timescale 1ps $end

 $scope module TOP $end
  $var wire  1 ( clk $end
  $var wire  1 $ io_clear $end
  $var wire  1 & io_full $end
  $var wire  8 % io_limit [7:0] $end
  $var wire  1 # io_tick $end
  $var wire  8 ' io_value [7:0] $end
  $var wire  1 ) reset $end
  $scope module Timer $end
   $var wire  1 ( clk $end
   $var wire  8 * counter [7:0] $end
   $var wire  1 $ io_clear $end
   $var wire  1 & io_full $end
   $var wire  8 % io_limit [7:0] $end
   $var wire  1 # io_tick $end
   $var wire  8 ' io_value [7:0] $end
   $var wire  1 ) reset $end
   $var wire  1 + when_Timer_l20 $end
  $upscope $end
 $upscope $end
$enddefinitions $end


#0
0#
0$
b11111111 %
0&
b00000000 '
0(
1)
b00000000 *
0+
#160
0)
#170
1$
1(
#175
0(
#180
0$
1(
#185
0(
#190
1(
#195
0(
#200
1#
1(
1+
#205
0(
#210
b00000001 '
1(
b00000001 *
#215
0(
#220
b00000010 '
1(
b00000010 *
#225
0(
#230
b00000011 '
1(
b00000011 *
#235
0(
#240
b00000100 '
1(
b00000100 *
#245
0(
#250
b00000101 '
1(
b00000101 *
#255
0(
#260
b00000110 '
1(
b00000110 *
#265
0(
#270
b00000111 '
1(
b00000111 *
#275
0(
#280
b00001000 '
1(
b00001000 *
#285
0(
#290
b00001001 '
1(
b00001001 *
#295
0(
#300
b00001010 '
1(
b00001010 *
#305
0(
#310
b00001011 '
1(
b00001011 *
#315
0(
#320
b00001100 '
1(
b00001100 *
#325
0(
#330
b00001101 '
1(
b00001101 *
#335
0(
#340
b00001110 '
1(
b00001110 *
#345
0(
#350
b00001111 '
1(
b00001111 *
#355
0(
#360
0#
b00010000 '
1(
b00010000 *
0+
#365
0(
#370
1(
#375
0(
#380
1#
b00100000 %
1(
1+
#385
0(
#390
b00010001 '
1(
b00010001 *
#395
0(
#400
b00010010 '
1(
b00010010 *
#405
0(
#410
b00010011 '
1(
b00010011 *
#415
0(
#420
b00010100 '
1(
b00010100 *
#425
0(
#430
b00010101 '
1(
b00010101 *
#435
0(
#440
b00010110 '
1(
b00010110 *
#445
0(
#450
b00010111 '
1(
b00010111 *
#455
0(
#460
b00011000 '
1(
b00011000 *
#465
0(
#470
b00011001 '
1(
b00011001 *
#475
0(
#480
b00011010 '
1(
b00011010 *
#485
0(
#490
b00011011 '
1(
b00011011 *
#495
0(
#500
b00011100 '
1(
b00011100 *
#505
0(
#510
b00011101 '
1(
b00011101 *
#515
0(
#520
b00011110 '
1(
b00011110 *
#525
0(
#530
b00011111 '
1(
b00011111 *
#535
0(
#540
1&
b00100000 '
1(
b00100000 *
0+
#545
0(
#550
1(
#555
0(
#560
1(
#565
0(
#570
1(
#575
0(
#580
1(
#585
0(
#590
1(
#595
0(
#600
1(
#605
0(
#610
1(
#615
0(
#620
1(
#625
0(
#630
1(
#635
0(
#640
1(
#645
0(
#650
0#
1$
1(
#655
0(
#660
0$
0&
b00000000 '
1(
b00000000 *
