tmp/job_1/PrimeUsage.v
// Generator : SpinalHDL v1.6.4    git head : 598c18959149eb18e5eee5b0aa3eef01ecaa41a1
// Component : PrimeUsage
// Git hash  : 89d7543c7219f82d1991c9174f1b313aba4435ca

`timescale 1ns/1ps 

module PrimeUsage (
  input      [4:0]    io_value,
  output              io_isPrime
);

  wire       [4:0]    _zz_io_isPrime;
  wire                _zz_io_isPrime_1;
  wire       [0:0]    _zz_io_isPrime_2;
  wire       [5:0]    _zz_io_isPrime_3;

  assign _zz_io_isPrime = 5'h11;
  assign _zz_io_isPrime_1 = (io_value == 5'h0d);
  assign _zz_io_isPrime_2 = (io_value == 5'h0b);
  assign _zz_io_isPrime_3 = {(io_value == 5'h07),{(io_value == 5'h05),{(io_value == 5'h03),{(io_value == 5'h02),{(io_value == 5'h01),(io_value == 5'h0)}}}}};
  assign io_isPrime = ({(io_value == 5'h1f),{(io_value == 5'h1d),{(io_value == 5'h17),{(io_value == 5'h13),{(io_value == _zz_io_isPrime),{_zz_io_isPrime_1,{_zz_io_isPrime_2,_zz_io_isPrime_3}}}}}}} != 13'h0);

endmodule

waves/PrimeUsage/test.vcd
$version Generated by VerilatedVcd $end
$date jeu. 07 avril 2022 16:43:44 $end
$timescale 1ps $end

 $scope module TOP $end
  $var wire  1 $ io_isPrime $end
  $var wire  5 # io_value [4:0] $end
  $scope module PrimeUsage $end
   $var wire  1 $ io_isPrime $end
   $var wire  5 # io_value [4:0] $end
  $upscope $end
 $upscope $end
$enddefinitions $end


#0
b00010 #
1$
#1
b11010 #
0$
#2
b11111 #
1$
#3
b00011 #
#4
b01110 #
0$
#5
b10110 #
#6
b01001 #
#7
b10000 #
#8
b01010 #
#9
b10000 #
#10
b11111 #
1$
#11
b10110 #
0$
#12
b01001 #
#13
b11100 #
#14
b10100 #
#15
b10000 #
#16
b00001 #
1$
#17
b10101 #
0$
#18
b00011 #
1$
#19
b11001 #
0$
#20
b11011 #
#21
b00001 #
1$
#22
b11001 #
0$
#23
b10101 #
#24
b01010 #
#25
b11000 #
#26
b10100 #
#27
b10000 #
#28
b11110 #
#29
b00110 #
#30
b01101 #
1$
#31
b00111 #
#32
b11001 #
0$
#33
b10000 #
#34
b10010 #
#35
b00111 #
1$
#36
b00010 #
#37
b10101 #
0$
#38
b11000 #
#39
b10100 #
#40
b11001 #
#41
b10101 #
#42
b01111 #
#43
b01011 #
1$
#44
b01100 #
0$
#45
b10110 #
#46
b10111 #
1$
#47
b01010 #
0$
#48
b01000 #
#49
b00101 #
1$
#50
b10010 #
0$
#51
b01111 #
#52
b10010 #
#53
b11010 #
#54
#55
b11111 #
1$
#56
b10110 #
0$
#57
b00000 #
1$
#58
b10101 #
0$
#59
b01000 #
#60
b00000 #
1$
#61
b10101 #
0$
#62
b00111 #
1$
#63
b01001 #
0$
#64
b01010 #
#65
b01101 #
1$
#66
b01000 #
0$
#67
b10001 #
1$
#68
b10101 #
0$
#69
b11011 #
#70
b10110 #
#71
b00110 #
#72
b11101 #
1$
#73
b10011 #
#74
b01011 #
#75
b01000 #
0$
#76
b00111 #
1$
#77
b01010 #
0$
#78
b10010 #
#79
b10110 #
#80
b11100 #
#81
b00000 #
1$
#82
b10111 #
#83
b01111 #
0$
#84
b11011 #
#85
b00000 #
1$
#86
b11110 #
0$
#87
b11011 #
#88
b01010 #
#89
b00110 #
#90
b10110 #
#91
b01100 #
#92
b01110 #
#93
b00001 #
1$
#94
b01110 #
0$
#95
b00000 #
1$
#96
b11100 #
0$
#97
b11001 #
#98
b00111 #
1$
#99
b01001 #
0$
