rtl/ApbPwm.vhd
-- Generator : SpinalHDL v1.6.4    git head : 598c18959149eb18e5eee5b0aa3eef01ecaa41a1
-- Component : ApbPwm
-- Git hash  : 89d7543c7219f82d1991c9174f1b313aba4435ca

library IEEE;
use IEEE.STD_LOGIC_1164.ALL;
use IEEE.NUMERIC_STD.all;

package pkg_enum is

end pkg_enum;

library IEEE;
use ieee.std_logic_1164.all;
use ieee.numeric_std.all;
use ieee.math_real.all;

package pkg_scala2hdl is
  function pkg_extract (that : std_logic_vector; bitId : integer) return std_logic;
  function pkg_extract (that : std_logic_vector; base : unsigned; size : integer) return std_logic_vector;
  function pkg_cat (a : std_logic_vector; b : std_logic_vector) return std_logic_vector;
  function pkg_not (value : std_logic_vector) return std_logic_vector;
  function pkg_extract (that : unsigned; bitId : integer) return std_logic;
  function pkg_extract (that : unsigned; base : unsigned; size : integer) return unsigned;
  function pkg_cat (a : unsigned; b : unsigned) return unsigned;
  function pkg_not (value : unsigned) return unsigned;
  function pkg_extract (that : signed; bitId : integer) return std_logic;
  function pkg_extract (that : signed; base : unsigned; size : integer) return signed;
  function pkg_cat (a : signed; b : signed) return signed;
  function pkg_not (value : signed) return signed;

  function pkg_mux (sel : std_logic; one : std_logic; zero : std_logic) return std_logic;
  function pkg_mux (sel : std_logic; one : std_logic_vector; zero : std_logic_vector) return std_logic_vector;
  function pkg_mux (sel : std_logic; one : unsigned; zero : unsigned) return unsigned;
  function pkg_mux (sel : std_logic; one : signed; zero : signed) return signed;

  function pkg_toStdLogic (value : boolean) return std_logic;
  function pkg_toStdLogicVector (value : std_logic) return std_logic_vector;
  function pkg_toUnsigned (value : std_logic) return unsigned;
  function pkg_toSigned (value : std_logic) return signed;
  function pkg_stdLogicVector (lit : std_logic_vector) return std_logic_vector;
  function pkg_unsigned (lit : unsigned) return unsigned;
  function pkg_signed (lit : signed) return signed;

  function pkg_resize (that : std_logic_vector; width : integer) return std_logic_vector;
  function pkg_resize (that : unsigned; width : integer) return unsigned;
  function pkg_resize (that : signed; width : integer) return signed;

  function pkg_extract (that : std_logic_vector; high : integer; low : integer) return std_logic_vector;
  function pkg_extract (that : unsigned; high : integer; low : integer) return unsigned;
  function pkg_extract (that : signed; high : integer; low : integer) return signed;

  function pkg_shiftRight (that : std_logic_vector; size : natural) return std_logic_vector;
  function pkg_shiftRight (that : std_logic_vector; size : unsigned) return std_logic_vector;
  function pkg_shiftLeft (that : std_logic_vector; size : natural) return std_logic_vector;
  function pkg_shiftLeft (that : std_logic_vector; size : unsigned) return std_logic_vector;

  function pkg_shiftRight (that : unsigned; size : natural) return unsigned;
  function pkg_shiftRight (that : unsigned; size : unsigned) return unsigned;
  function pkg_shiftLeft (that : unsigned; size : natural) return unsigned;
  function pkg_shiftLeft (that : unsigned; size : unsigned) return unsigned;

  function pkg_shiftRight (that : signed; size : natural) return signed;
  function pkg_shiftRight (that : signed; size : unsigned) return signed;
  function pkg_shiftLeft (that : signed; size : natural) return signed;
  function pkg_shiftLeft (that : signed; size : unsigned; w : integer) return signed;

  function pkg_rotateLeft (that : std_logic_vector; size : unsigned) return std_logic_vector;
end  pkg_scala2hdl;

package body pkg_scala2hdl is
  function pkg_extract (that : std_logic_vector; bitId : integer) return std_logic is
    alias temp : std_logic_vector(that'length-1 downto 0) is that;
  begin
    if bitId >= temp'length then
      return 'U';
    end if;
    return temp(bitId);
  end pkg_extract;

  function pkg_extract (that : std_logic_vector; base : unsigned; size : integer) return std_logic_vector is
    alias temp : std_logic_vector(that'length-1 downto 0) is that;    constant elementCount : integer := temp'length - size + 1;
    type tableType is array (0 to elementCount-1) of std_logic_vector(size-1 downto 0);
    variable table : tableType;
  begin
    for i in 0 to elementCount-1 loop
      table(i) := temp(i + size - 1 downto i);
    end loop;
    if base + size >= elementCount then
      return (size-1 downto 0 => 'U');
    end if;
    return table(to_integer(base));
  end pkg_extract;

  function pkg_cat (a : std_logic_vector; b : std_logic_vector) return std_logic_vector is
    variable cat : std_logic_vector(a'length + b'length-1 downto 0);
  begin
    cat := a & b;
    return cat;
  end pkg_cat;

  function pkg_not (value : std_logic_vector) return std_logic_vector is
    variable ret : std_logic_vector(value'length-1 downto 0);
  begin
    ret := not value;
    return ret;
  end pkg_not;

  function pkg_extract (that : unsigned; bitId : integer) return std_logic is
    alias temp : unsigned(that'length-1 downto 0) is that;
  begin
    if bitId >= temp'length then
      return 'U';
    end if;
    return temp(bitId);
  end pkg_extract;

  function pkg_extract (that : unsigned; base : unsigned; size : integer) return unsigned is
    alias temp : unsigned(that'length-1 downto 0) is that;    constant elementCount : integer := temp'length - size + 1;
    type tableType is array (0 to elementCount-1) of unsigned(size-1 downto 0);
    variable table : tableType;
  begin
    for i in 0 to elementCount-1 loop
      table(i) := temp(i + size - 1 downto i);
    end loop;
    if base + size >= elementCount then
      return (size-1 downto 0 => 'U');
    end if;
    return table(to_integer(base));
  end pkg_extract;

  function pkg_cat (a : unsigned; b : unsigned) return unsigned is
    variable cat : unsigned(a'length + b'length-1 downto 0);
  begin
    cat := a & b;
    return cat;
  end pkg_cat;

  function pkg_not (value : unsigned) return unsigned is
    variable ret : unsigned(value'length-1 downto 0);
  begin
    ret := not value;
    return ret;
  end pkg_not;

  function pkg_extract (that : signed; bitId : integer) return std_logic is
    alias temp : signed(that'length-1 downto 0) is that;
  begin
    if bitId >= temp'length then
      return 'U';
    end if;
    return temp(bitId);
  end pkg_extract;

  function pkg_extract (that : signed; base : unsigned; size : integer) return signed is
    alias temp : signed(that'length-1 downto 0) is that;    constant elementCount : integer := temp'length - size + 1;
    type tableType is array (0 to elementCount-1) of signed(size-1 downto 0);
    variable table : tableType;
  begin
    for i in 0 to elementCount-1 loop
      table(i) := temp(i + size - 1 downto i);
    end loop;
    if base + size >= elementCount then
      return (size-1 downto 0 => 'U');
    end if;
    return table(to_integer(base));
  end pkg_extract;

  function pkg_cat (a : signed; b : signed) return signed is
    variable cat : signed(a'length + b'length-1 downto 0);
  begin
    cat := a & b;
    return cat;
  end pkg_cat;

  function pkg_not (value : signed) return signed is
    variable ret : signed(value'length-1 downto 0);
  begin
    ret := not value;
    return ret;
  end pkg_not;


  -- unsigned shifts
  function pkg_shiftRight (that : unsigned; size : natural) return unsigned is
    variable ret : unsigned(that'length-1 downto 0);
  begin
    if size >= that'length then
      return "";
    else
      ret := shift_right(that,size);
      return ret(that'length-1-size downto 0);
    end if;
  end pkg_shiftRight;

  function pkg_shiftRight (that : unsigned; size : unsigned) return unsigned is
    variable ret : unsigned(that'length-1 downto 0);
  begin
    ret := shift_right(that,to_integer(size));
    return ret;
  end pkg_shiftRight;

  function pkg_shiftLeft (that : unsigned; size : natural) return unsigned is
  begin
    return shift_left(resize(that,that'length + size),size);
  end pkg_shiftLeft;

  function pkg_shiftLeft (that : unsigned; size : unsigned) return unsigned is
  begin
    return shift_left(resize(that,that'length + 2**size'length - 1),to_integer(size));
  end pkg_shiftLeft;

  -- std_logic_vector shifts
  function pkg_shiftRight (that : std_logic_vector; size : natural) return std_logic_vector is
  begin
    return std_logic_vector(pkg_shiftRight(unsigned(that),size));
  end pkg_shiftRight;

  function pkg_shiftRight (that : std_logic_vector; size : unsigned) return std_logic_vector is
  begin
    return std_logic_vector(pkg_shiftRight(unsigned(that),size));
  end pkg_shiftRight;

  function pkg_shiftLeft (that : std_logic_vector; size : natural) return std_logic_vector is
  begin
    return std_logic_vector(pkg_shiftLeft(unsigned(that),size));
  end pkg_shiftLeft;

  function pkg_shiftLeft (that : std_logic_vector; size : unsigned) return std_logic_vector is
  begin
    return std_logic_vector(pkg_shiftLeft(unsigned(that),size));
  end pkg_shiftLeft;

  -- signed shifts
  function pkg_shiftRight (that : signed; size : natural) return signed is
  begin
    return signed(pkg_shiftRight(unsigned(that),size));
  end pkg_shiftRight;

  function pkg_shiftRight (that : signed; size : unsigned) return signed is
  begin
    return shift_right(that,to_integer(size));
  end pkg_shiftRight;

  function pkg_shiftLeft (that : signed; size : natural) return signed is
  begin
    return signed(pkg_shiftLeft(unsigned(that),size));
  end pkg_shiftLeft;

  function pkg_shiftLeft (that : signed; size : unsigned; w : integer) return signed is
  begin
    return shift_left(resize(that,w),to_integer(size));
  end pkg_shiftLeft;

  function pkg_rotateLeft (that : std_logic_vector; size : unsigned) return std_logic_vector is
  begin
    return std_logic_vector(rotate_left(unsigned(that),to_integer(size)));
  end pkg_rotateLeft;

  function pkg_extract (that : std_logic_vector; high : integer; low : integer) return std_logic_vector is
    alias temp : std_logic_vector(that'length-1 downto 0) is that;
  begin
    return temp(high downto low);
  end pkg_extract;

  function pkg_extract (that : unsigned; high : integer; low : integer) return unsigned is
    alias temp : unsigned(that'length-1 downto 0) is that;
  begin
    return temp(high downto low);
  end pkg_extract;

  function pkg_extract (that : signed; high : integer; low : integer) return signed is
    alias temp : signed(that'length-1 downto 0) is that;
  begin
    return temp(high downto low);
  end pkg_extract;

  function pkg_mux (sel : std_logic; one : std_logic; zero : std_logic) return std_logic is
  begin
    if sel = '1' then
      return one;
    else
      return zero;
    end if;
  end pkg_mux;

  function pkg_mux (sel : std_logic; one : std_logic_vector; zero : std_logic_vector) return std_logic_vector is
    variable ret : std_logic_vector(zero'range);
  begin
    if sel = '1' then
      ret := one;
    else
      ret := zero;
    end if;
    return ret;
  end pkg_mux;

  function pkg_mux (sel : std_logic; one : unsigned; zero : unsigned) return unsigned is
    variable ret : unsigned(zero'range);
  begin
    if sel = '1' then
      ret := one;
    else
      ret := zero;
    end if;
    return ret;
  end pkg_mux;

  function pkg_mux (sel : std_logic; one : signed; zero : signed) return signed is
    variable ret : signed(zero'range);
  begin
    if sel = '1' then
      ret := one;
    else
      ret := zero;
    end if;
    return ret;
  end pkg_mux;

  function pkg_toStdLogic (value : boolean) return std_logic is
  begin
    if value = true then
      return '1';
    else
      return '0';
    end if;
  end pkg_toStdLogic;

  function pkg_toStdLogicVector (value : std_logic) return std_logic_vector is
    variable ret : std_logic_vector(0 downto 0);
  begin
    ret(0) := value;
    return ret;
  end pkg_toStdLogicVector;

  function pkg_toUnsigned (value : std_logic) return unsigned is
    variable ret : unsigned(0 downto 0);
  begin
    ret(0) := value;
    return ret;
  end pkg_toUnsigned;

  function pkg_toSigned (value : std_logic) return signed is
    variable ret : signed(0 downto 0);
  begin
    ret(0) := value;
    return ret;
  end pkg_toSigned;

  function pkg_stdLogicVector (lit : std_logic_vector) return std_logic_vector is
    alias ret : std_logic_vector(lit'length-1 downto 0) is lit;
  begin
    return ret;
  end pkg_stdLogicVector;

  function pkg_unsigned (lit : unsigned) return unsigned is
    alias ret : unsigned(lit'length-1 downto 0) is lit;
  begin
    return ret;
  end pkg_unsigned;

  function pkg_signed (lit : signed) return signed is
    alias ret : signed(lit'length-1 downto 0) is lit;
  begin
    return ret;
  end pkg_signed;

  function pkg_resize (that : std_logic_vector; width : integer) return std_logic_vector is
  begin
    return std_logic_vector(resize(unsigned(that),width));
  end pkg_resize;

  function pkg_resize (that : unsigned; width : integer) return unsigned is
    variable ret : unsigned(width-1 downto 0);
  begin
    if that'length = 0 then
       ret := (others => '0');
    else
       ret := resize(that,width);
    end if;
    return ret;
  end pkg_resize;
  function pkg_resize (that : signed; width : integer) return signed is
    alias temp : signed(that'length-1 downto 0) is that;
    variable ret : signed(width-1 downto 0);
  begin
    if temp'length = 0 then
       ret := (others => '0');
    elsif temp'length >= width then
       ret := temp(width-1 downto 0);
    else
       ret := resize(temp,width);
    end if;
    return ret;
  end pkg_resize;
end pkg_scala2hdl;


library ieee;
use ieee.std_logic_1164.all;
use ieee.numeric_std.all;

library work;
use work.pkg_scala2hdl.all;
use work.all;
use work.pkg_enum.all;


entity ApbPwm is
  port(
    io_apb_PADDR : in unsigned(7 downto 0);
    io_apb_PSEL : in std_logic_vector(0 downto 0);
    io_apb_PENABLE : in std_logic;
    io_apb_PWRITE : in std_logic;
    io_apb_PWDATA : in std_logic_vector(31 downto 0);
    io_apb_PRDATA : out std_logic_vector(31 downto 0);
    io_apb_PREADY : out std_logic;
    io_pwm : out std_logic;
    clk : in std_logic;
    reset : in std_logic
  );
end ApbPwm;

architecture arch of ApbPwm is

  signal logic_enable : std_logic;
  signal logic_dutyCycle : unsigned(7 downto 0);
  signal logic_timer : unsigned(7 downto 0);
  signal logic_output : std_logic;
  signal control_isWrite : std_logic;
begin
  io_pwm <= logic_output;
  control_isWrite <= ((pkg_extract(io_apb_PSEL,0) and io_apb_PWRITE) and io_apb_PENABLE);
  process(io_apb_PADDR,logic_enable,logic_dutyCycle)
  begin
    io_apb_PRDATA <= pkg_stdLogicVector("00000000000000000000000000000000");
    case io_apb_PADDR is
      when "00000000" =>
        io_apb_PRDATA(0) <= logic_enable;
      when "00000100" =>
        io_apb_PRDATA <= pkg_resize(std_logic_vector(logic_dutyCycle),32);
      when others =>
    end case;
  end process;

  io_apb_PREADY <= pkg_toStdLogic(true);
  process(clk, reset)
  begin
    if reset = '1' then
      logic_enable <= pkg_toStdLogic(false);
      logic_timer <= pkg_unsigned("00000000");
      logic_output <= pkg_toStdLogic(false);
    elsif rising_edge(clk) then
      if logic_enable = '1' then
        logic_timer <= (logic_timer + pkg_unsigned("00000001"));
      end if;
      logic_output <= pkg_toStdLogic(logic_timer < logic_dutyCycle);
      case io_apb_PADDR is
        when "00000000" =>
          if control_isWrite = '1' then
            logic_enable <= pkg_extract(io_apb_PWDATA,0);
          end if;
        when others =>
      end case;
    end if;
  end process;

  process(clk)
  begin
    if rising_edge(clk) then
      case io_apb_PADDR is
        when "00000100" =>
          if control_isWrite = '1' then
            logic_dutyCycle <= pkg_resize(unsigned(io_apb_PWDATA),8);
          end if;
        when others =>
      end case;
    end if;
  end process;

end arch;

waves/ApbPwm/test.vcd
$version Generated by VerilatedVcd $end
$date mer. 06 avril 2022 16:52:11 $end
$timescale 1ps $end

 $scope module TOP $end
  $var wire  1 . clk $end
  $var wire  8 & io_apb_PADDR [7:0] $end
  $var wire  1 ( io_apb_PENABLE $end
  $var wire 32 + io_apb_PRDATA [31:0] $end
  $var wire  1 , io_apb_PREADY $end
  $var wire  1 ' io_apb_PSEL [0:0] $end
  $var wire 32 * io_apb_PWDATA [31:0] $end
  $var wire  1 ) io_apb_PWRITE $end
  $var wire  1 - io_pwm $end
  $var wire  1 / reset $end
  $scope module ApbPwm $end
   $var wire  1 . clk $end
   $var wire  1 1 control_isWrite $end
   $var wire  8 & io_apb_PADDR [7:0] $end
   $var wire  1 ( io_apb_PENABLE $end
   $var wire 32 + io_apb_PRDATA [31:0] $end
   $var wire  1 , io_apb_PREADY $end
   $var wire  1 ' io_apb_PSEL [0:0] $end
   $var wire 32 * io_apb_PWDATA [31:0] $end
   $var wire  1 ) io_apb_PWRITE $end
   $var wire  1 - io_pwm $end
   $var wire  8 0 logic_dutyCycle [7:0] $end
   $var wire  1 # logic_enable $end
   $var wire  1 % logic_output $end
   $var wire  8 $ logic_timer [7:0] $end
   $var wire  1 / reset $end
  $upscope $end
 $upscope $end
$enddefinitions $end


#0
0#
b00000000 $
0%
b00000100 &
1'
0(
1)
b00000000000000000000000011000000 *
b00000000000000000000000010000110 +
1,
0-
0.
1/
b10000110 0
01
#160
0/
#170
1%
1(
1-
1.
11
#175
0.
#180
b00000000 &
0(
b00000000000000000000000000000001 *
b00000000000000000000000000000000 +
1.
b11000000 0
01
#185
0.
#190
1(
1.
11
#195
0.
#200
1#
b01100001 &
0'
b00011111100011000001010110110110 *
1.
01
#205
0.
#210
b00000001 $
1.
#215
0.
#220
b00000010 $
1.
#225
0.
#230
b00000011 $
1.
#235
0.
#240
b00000100 $
1.
#245
0.
#250
b00000101 $
1.
#255
0.
#260
b00000110 $
1.
#265
0.
#270
b00000111 $
1.
#275
0.
#280
b00001000 $
1.
#285
0.
#290
b00001001 $
1.
#295
0.
#300
b00001010 $
1.
#305
0.
#310
b00001011 $
1.
#315
0.
#320
b00001100 $
1.
#325
0.
#330
b00001101 $
1.
#335
0.
#340
b00001110 $
1.
#345
0.
#350
b00001111 $
1.
#355
0.
#360
b00010000 $
1.
#365
0.
#370
b00010001 $
1.
#375
0.
#380
b00010010 $
1.
#385
0.
#390
b00010011 $
1.
#395
0.
#400
b00010100 $
1.
#405
0.
#410
b00010101 $
1.
#415
0.
#420
b00010110 $
1.
#425
0.
#430
b00010111 $
1.
#435
0.
#440
b00011000 $
1.
#445
0.
#450
b00011001 $
1.
#455
0.
#460
b00011010 $
1.
#465
0.
#470
b00011011 $
1.
#475
0.
#480
b00011100 $
1.
#485
0.
#490
b00011101 $
1.
#495
0.
#500
b00011110 $
1.
#505
0.
#510
b00011111 $
1.
#515
0.
#520
b00100000 $
1.
#525
0.
#530
b00100001 $
1.
#535
0.
#540
b00100010 $
1.
#545
0.
#550
b00100011 $
1.
#555
0.
#560
b00100100 $
1.
#565
0.
#570
b00100101 $
1.
#575
0.
#580
b00100110 $
1.
#585
0.
#590
b00100111 $
1.
#595
0.
#600
b00101000 $
1.
#605
0.
#610
b00101001 $
1.
#615
0.
#620
b00101010 $
1.
#625
0.
#630
b00101011 $
1.
#635
0.
#640
b00101100 $
1.
#645
0.
#650
b00101101 $
1.
#655
0.
#660
b00101110 $
1.
#665
0.
#670
b00101111 $
1.
#675
0.
#680
b00110000 $
1.
#685
0.
#690
b00110001 $
1.
#695
0.
#700
b00110010 $
1.
#705
0.
#710
b00110011 $
1.
#715
0.
#720
b00110100 $
1.
#725
0.
#730
b00110101 $
1.
#735
0.
#740
b00110110 $
1.
#745
0.
#750
b00110111 $
1.
#755
0.
#760
b00111000 $
1.
#765
0.
#770
b00111001 $
1.
#775
0.
#780
b00111010 $
1.
#785
0.
#790
b00111011 $
1.
#795
0.
#800
b00111100 $
1.
#805
0.
#810
b00111101 $
1.
#815
0.
#820
b00111110 $
1.
#825
0.
#830
b00111111 $
1.
#835
0.
#840
b01000000 $
1.
#845
0.
#850
b01000001 $
1.
#855
0.
#860
b01000010 $
1.
#865
0.
#870
b01000011 $
1.
#875
0.
#880
b01000100 $
1.
#885
0.
#890
b01000101 $
1.
#895
0.
#900
b01000110 $
1.
#905
0.
#910
b01000111 $
1.
#915
0.
#920
b01001000 $
1.
#925
0.
#930
b01001001 $
1.
#935
0.
#940
b01001010 $
1.
#945
0.
#950
b01001011 $
1.
#955
0.
#960
b01001100 $
1.
#965
0.
#970
b01001101 $
1.
#975
0.
#980
b01001110 $
1.
#985
0.
#990
b01001111 $
1.
#995
0.
#1000
b01010000 $
1.
#1005
0.
#1010
b01010001 $
1.
#1015
0.
#1020
b01010010 $
1.
#1025
0.
#1030
b01010011 $
1.
#1035
0.
#1040
b01010100 $
1.
#1045
0.
#1050
b01010101 $
1.
#1055
0.
#1060
b01010110 $
1.
#1065
0.
#1070
b01010111 $
1.
#1075
0.
#1080
b01011000 $
1.
#1085
0.
#1090
b01011001 $
1.
#1095
0.
#1100
b01011010 $
1.
#1105
0.
#1110
b01011011 $
1.
#1115
0.
#1120
b01011100 $
1.
#1125
0.
#1130
b01011101 $
1.
#1135
0.
#1140
b01011110 $
1.
#1145
0.
#1150
b01011111 $
1.
#1155
0.
#1160
b01100000 $
1.
#1165
0.
#1170
b01100001 $
1.
#1175
0.
#1180
b01100010 $
1.
#1185
0.
#1190
b01100011 $
1.
#1195
0.
#1200
b01100100 $
1.
#1205
0.
#1210
b01100101 $
1.
#1215
0.
#1220
b01100110 $
1.
#1225
0.
#1230
b01100111 $
1.
#1235
0.
#1240
b01101000 $
1.
#1245
0.
#1250
b01101001 $
1.
#1255
0.
#1260
b01101010 $
1.
#1265
0.
#1270
b01101011 $
1.
#1275
0.
#1280
b01101100 $
1.
#1285
0.
#1290
b01101101 $
1.
#1295
0.
#1300
b01101110 $
1.
#1305
0.
#1310
b01101111 $
1.
#1315
0.
#1320
b01110000 $
1.
#1325
0.
#1330
b01110001 $
1.
#1335
0.
#1340
b01110010 $
1.
#1345
0.
#1350
b01110011 $
1.
#1355
0.
#1360
b01110100 $
1.
#1365
0.
#1370
b01110101 $
1.
#1375
0.
#1380
b01110110 $
1.
#1385
0.
#1390
b01110111 $
1.
#1395
0.
#1400
b01111000 $
1.
#1405
0.
#1410
b01111001 $
1.
#1415
0.
#1420
b01111010 $
1.
#1425
0.
#1430
b01111011 $
1.
#1435
0.
#1440
b01111100 $
1.
#1445
0.
#1450
b01111101 $
1.
#1455
0.
#1460
b01111110 $
1.
#1465
0.
#1470
b01111111 $
1.
#1475
0.
#1480
b10000000 $
1.
#1485
0.
#1490
b10000001 $
1.
#1495
0.
#1500
b10000010 $
1.
#1505
0.
#1510
b10000011 $
1.
#1515
0.
#1520
b10000100 $
1.
#1525
0.
#1530
b10000101 $
1.
#1535
0.
#1540
b10000110 $
1.
#1545
0.
#1550
b10000111 $
1.
#1555
0.
#1560
b10001000 $
1.
#1565
0.
#1570
b10001001 $
1.
#1575
0.
#1580
b10001010 $
1.
#1585
0.
#1590
b10001011 $
1.
#1595
0.
#1600
b10001100 $
1.
#1605
0.
#1610
b10001101 $
1.
#1615
0.
#1620
b10001110 $
1.
#1625
0.
#1630
b10001111 $
1.
#1635
0.
#1640
b10010000 $
1.
#1645
0.
#1650
b10010001 $
1.
#1655
0.
#1660
b10010010 $
1.
#1665
0.
#1670
b10010011 $
1.
#1675
0.
#1680
b10010100 $
1.
#1685
0.
#1690
b10010101 $
1.
#1695
0.
#1700
b10010110 $
1.
#1705
0.
#1710
b10010111 $
1.
#1715
0.
#1720
b10011000 $
1.
#1725
0.
#1730
b10011001 $
1.
#1735
0.
#1740
b10011010 $
1.
#1745
0.
#1750
b10011011 $
1.
#1755
0.
#1760
b10011100 $
1.
#1765
0.
#1770
b10011101 $
1.
#1775
0.
#1780
b10011110 $
1.
#1785
0.
#1790
b10011111 $
1.
#1795
0.
#1800
b10100000 $
1.
#1805
0.
#1810
b10100001 $
1.
#1815
0.
#1820
b10100010 $
1.
#1825
0.
#1830
b10100011 $
1.
#1835
0.
#1840
b10100100 $
1.
#1845
0.
#1850
b10100101 $
1.
#1855
0.
#1860
b10100110 $
1.
#1865
0.
#1870
b10100111 $
1.
#1875
0.
#1880
b10101000 $
1.
#1885
0.
#1890
b10101001 $
1.
#1895
0.
#1900
b10101010 $
1.
#1905
0.
#1910
b10101011 $
1.
#1915
0.
#1920
b10101100 $
1.
#1925
0.
#1930
b10101101 $
1.
#1935
0.
#1940
b10101110 $
1.
#1945
0.
#1950
b10101111 $
1.
#1955
0.
#1960
b10110000 $
1.
#1965
0.
#1970
b10110001 $
1.
#1975
0.
#1980
b10110010 $
1.
#1985
0.
#1990
b10110011 $
1.
#1995
0.
#2000
b10110100 $
1.
#2005
0.
#2010
b10110101 $
1.
#2015
0.
#2020
b10110110 $
1.
#2025
0.
#2030
b10110111 $
1.
#2035
0.
#2040
b10111000 $
1.
#2045
0.
#2050
b10111001 $
1.
#2055
0.
#2060
b10111010 $
1.
#2065
0.
#2070
b10111011 $
1.
#2075
0.
#2080
b10111100 $
1.
#2085
0.
#2090
b10111101 $
1.
#2095
0.
#2100
b10111110 $
1.
#2105
0.
#2110
b10111111 $
1.
#2115
0.
#2120
b11000000 $
1.
#2125
0.
#2130
b11000001 $
0%
0-
1.
#2135
0.
#2140
b11000010 $
1.
#2145
0.
#2150
b11000011 $
1.
#2155
0.
#2160
b11000100 $
1.
#2165
0.
#2170
b11000101 $
1.
#2175
0.
#2180
b11000110 $
1.
#2185
0.
#2190
b11000111 $
1.
#2195
0.
#2200
b11001000 $
1.
#2205
0.
#2210
b11001001 $
1.
#2215
0.
#2220
b11001010 $
1.
#2225
0.
#2230
b11001011 $
1.
#2235
0.
#2240
b11001100 $
1.
#2245
0.
#2250
b11001101 $
1.
#2255
0.
#2260
b11001110 $
1.
#2265
0.
#2270
b11001111 $
1.
#2275
0.
#2280
b11010000 $
1.
#2285
0.
#2290
b11010001 $
1.
#2295
0.
#2300
b11010010 $
1.
#2305
0.
#2310
b11010011 $
1.
#2315
0.
#2320
b11010100 $
1.
#2325
0.
#2330
b11010101 $
1.
#2335
0.
#2340
b11010110 $
1.
#2345
0.
#2350
b11010111 $
1.
#2355
0.
#2360
b11011000 $
1.
#2365
0.
#2370
b11011001 $
1.
#2375
0.
#2380
b11011010 $
1.
#2385
0.
#2390
b11011011 $
1.
#2395
0.
#2400
b11011100 $
1.
#2405
0.
#2410
b11011101 $
1.
#2415
0.
#2420
b11011110 $
1.
#2425
0.
#2430
b11011111 $
1.
#2435
0.
#2440
b11100000 $
1.
#2445
0.
#2450
b11100001 $
1.
#2455
0.
#2460
b11100010 $
1.
#2465
0.
#2470
b11100011 $
1.
#2475
0.
#2480
b11100100 $
1.
#2485
0.
#2490
b11100101 $
1.
#2495
0.
#2500
b11100110 $
1.
#2505
0.
#2510
b11100111 $
1.
#2515
0.
#2520
b11101000 $
1.
#2525
0.
#2530
b11101001 $
1.
#2535
0.
#2540
b11101010 $
1.
#2545
0.
#2550
b11101011 $
1.
#2555
0.
#2560
b11101100 $
1.
#2565
0.
#2570
b11101101 $
1.
#2575
0.
#2580
b11101110 $
1.
#2585
0.
#2590
b11101111 $
1.
#2595
0.
#2600
b11110000 $
1.
#2605
0.
#2610
b11110001 $
1.
#2615
0.
#2620
b11110010 $
1.
#2625
0.
#2630
b11110011 $
1.
#2635
0.
#2640
b11110100 $
1.
#2645
0.
#2650
b11110101 $
1.
#2655
0.
#2660
b11110110 $
1.
#2665
0.
#2670
b11110111 $
1.
#2675
0.
#2680
b11111000 $
1.
#2685
0.
#2690
b11111001 $
1.
#2695
0.
#2700
b11111010 $
1.
#2705
0.
#2710
b11111011 $
1.
#2715
0.
#2720
b11111100 $
1.
#2725
0.
#2730
b11111101 $
1.
#2735
0.
#2740
b11111110 $
1.
#2745
0.
#2750
b11111111 $
1.
#2755
0.
#2760
b00000000 $
1.
#2765
0.
#2770
b00000001 $
1%
1-
1.
#2775
0.
#2780
b00000010 $
1.
#2785
0.
#2790
b00000011 $
1.
#2795
0.
#2800
b00000100 $
1.
#2805
0.
#2810
b00000101 $
1.
#2815
0.
#2820
b00000110 $
1.
#2825
0.
#2830
b00000111 $
1.
#2835
0.
#2840
b00001000 $
1.
#2845
0.
#2850
b00001001 $
1.
#2855
0.
#2860
b00001010 $
1.
#2865
0.
#2870
b00001011 $
1.
#2875
0.
#2880
b00001100 $
1.
#2885
0.
#2890
b00001101 $
1.
#2895
0.
#2900
b00001110 $
1.
#2905
0.
#2910
b00001111 $
1.
#2915
0.
#2920
b00010000 $
1.
#2925
0.
#2930
b00010001 $
1.
#2935
0.
#2940
b00010010 $
1.
#2945
0.
#2950
b00010011 $
1.
#2955
0.
#2960
b00010100 $
1.
#2965
0.
#2970
b00010101 $
1.
#2975
0.
#2980
b00010110 $
1.
#2985
0.
#2990
b00010111 $
1.
#2995
0.
#3000
b00011000 $
1.
#3005
0.
#3010
b00011001 $
1.
#3015
0.
#3020
b00011010 $
1.
#3025
0.
#3030
b00011011 $
1.
#3035
0.
#3040
b00011100 $
1.
#3045
0.
#3050
b00011101 $
1.
#3055
0.
#3060
b00011110 $
1.
#3065
0.
#3070
b00011111 $
1.
#3075
0.
#3080
b00100000 $
1.
#3085
0.
#3090
b00100001 $
1.
#3095
0.
#3100
b00100010 $
1.
#3105
0.
#3110
b00100011 $
1.
#3115
0.
#3120
b00100100 $
1.
#3125
0.
#3130
b00100101 $
1.
#3135
0.
#3140
b00100110 $
1.
#3145
0.
#3150
b00100111 $
1.
#3155
0.
#3160
b00101000 $
1.
#3165
0.
#3170
b00101001 $
1.
#3175
0.
#3180
b00101010 $
1.
#3185
0.
#3190
b00101011 $
1.
#3195
0.
#3200
b00101100 $
1.
#3205
0.
#3210
b00101101 $
1.
#3215
0.
#3220
b00101110 $
1.
#3225
0.
#3230
b00101111 $
1.
#3235
0.
#3240
b00110000 $
1.
#3245
0.
#3250
b00110001 $
1.
#3255
0.
#3260
b00110010 $
1.
#3265
0.
#3270
b00110011 $
1.
#3275
0.
#3280
b00110100 $
1.
#3285
0.
#3290
b00110101 $
1.
#3295
0.
#3300
b00110110 $
1.
#3305
0.
#3310
b00110111 $
1.
#3315
0.
#3320
b00111000 $
1.
#3325
0.
#3330
b00111001 $
1.
#3335
0.
#3340
b00111010 $
1.
#3345
0.
#3350
b00111011 $
1.
#3355
0.
#3360
b00111100 $
1.
#3365
0.
#3370
b00111101 $
1.
#3375
0.
#3380
b00111110 $
1.
#3385
0.
#3390
b00111111 $
1.
#3395
0.
#3400
b01000000 $
1.
#3405
0.
#3410
b01000001 $
1.
#3415
0.
#3420
b01000010 $
1.
#3425
0.
#3430
b01000011 $
1.
#3435
0.
#3440
b01000100 $
1.
#3445
0.
#3450
b01000101 $
1.
#3455
0.
#3460
b01000110 $
1.
#3465
0.
#3470
b01000111 $
1.
#3475
0.
#3480
b01001000 $
1.
#3485
0.
#3490
b01001001 $
1.
#3495
0.
#3500
b01001010 $
1.
#3505
0.
#3510
b01001011 $
1.
#3515
0.
#3520
b01001100 $
1.
#3525
0.
#3530
b01001101 $
1.
#3535
0.
#3540
b01001110 $
1.
#3545
0.
#3550
b01001111 $
1.
#3555
0.
#3560
b01010000 $
1.
#3565
0.
#3570
b01010001 $
1.
#3575
0.
#3580
b01010010 $
1.
#3585
0.
#3590
b01010011 $
1.
#3595
0.
#3600
b01010100 $
1.
#3605
0.
#3610
b01010101 $
1.
#3615
0.
#3620
b01010110 $
1.
#3625
0.
#3630
b01010111 $
1.
#3635
0.
#3640
b01011000 $
1.
#3645
0.
#3650
b01011001 $
1.
#3655
0.
#3660
b01011010 $
1.
#3665
0.
#3670
b01011011 $
1.
#3675
0.
#3680
b01011100 $
1.
#3685
0.
#3690
b01011101 $
1.
#3695
0.
#3700
b01011110 $
1.
